{
"meta":{"test_sets":[],"test_metrics":[],"learn_metrics":[{"best_value":"Min","name":"RMSE"}],"launch_mode":"Train","parameters":"","iteration_count":1000,"learn_sets":["learn"],"name":"experiment"},
"iterations":[
{"learn":[0.5294290295],"iteration":0,"passed_time":0.01059037614,"remaining_time":10.57978576},
{"learn":[0.5108007504],"iteration":1,"passed_time":0.02264419377,"remaining_time":11.29945269},
{"learn":[0.4934753585],"iteration":2,"passed_time":0.03373422885,"remaining_time":11.21100872},
{"learn":[0.4770831656],"iteration":3,"passed_time":0.04546185014,"remaining_time":11.32000068},
{"learn":[0.4632326455],"iteration":4,"passed_time":0.05708213478,"remaining_time":11.35934482},
{"learn":[0.4491054074],"iteration":5,"passed_time":0.06794186235,"remaining_time":11.25570186},
{"learn":[0.4355115805],"iteration":6,"passed_time":0.07921194054,"remaining_time":11.23677957},
{"learn":[0.423443239],"iteration":7,"passed_time":0.09057626099,"remaining_time":11.23145636},
{"learn":[0.4123935461],"iteration":8,"passed_time":0.1013115388,"remaining_time":11.1555261},
{"learn":[0.4019054547],"iteration":9,"passed_time":0.1123227568,"remaining_time":11.11995292},
{"learn":[0.3922287226],"iteration":10,"passed_time":0.124018416,"remaining_time":11.15038304},
{"learn":[0.383219661],"iteration":11,"passed_time":0.134948248,"remaining_time":11.11073909},
{"learn":[0.3751336811],"iteration":12,"passed_time":0.1457095161,"remaining_time":11.0627148},
{"learn":[0.3679617542],"iteration":13,"passed_time":0.1566951477,"remaining_time":11.0358154},
{"learn":[0.3614338227],"iteration":14,"passed_time":0.1673617736,"remaining_time":10.9900898},
{"learn":[0.3557150561],"iteration":15,"passed_time":0.1781485321,"remaining_time":10.95613472},
{"learn":[0.3497542691],"iteration":16,"passed_time":0.1893602121,"remaining_time":10.94947579},
{"learn":[0.344342111],"iteration":17,"passed_time":0.2002871048,"remaining_time":10.92677428},
{"learn":[0.3394551093],"iteration":18,"passed_time":0.2109048739,"remaining_time":10.88935165},
{"learn":[0.3346713247],"iteration":19,"passed_time":0.2225309388,"remaining_time":10.904016},
{"learn":[0.3304952814],"iteration":20,"passed_time":0.2328851489,"remaining_time":10.85688385},
{"learn":[0.3267342697],"iteration":21,"passed_time":0.2438904387,"remaining_time":10.84203859},
{"learn":[0.323162552],"iteration":22,"passed_time":0.2549427983,"remaining_time":10.8295267},
{"learn":[0.3200014898],"iteration":23,"passed_time":0.2661832713,"remaining_time":10.82478637},
{"learn":[0.3172937617],"iteration":24,"passed_time":0.2769030293,"remaining_time":10.79921814},
{"learn":[0.3145523929],"iteration":25,"passed_time":0.287922946,"remaining_time":10.78603652},
{"learn":[0.3119214051],"iteration":26,"passed_time":0.2984314107,"remaining_time":10.7545838},
{"learn":[0.3095181157],"iteration":27,"passed_time":0.3090111023,"remaining_time":10.72709969},
{"learn":[0.3071801256],"iteration":28,"passed_time":0.3207215283,"remaining_time":10.73864152},
{"learn":[0.3051629129],"iteration":29,"passed_time":0.3313828058,"remaining_time":10.71471072},
{"learn":[0.303173894],"iteration":30,"passed_time":0.3422376541,"remaining_time":10.69768667},
{"learn":[0.3011378141],"iteration":31,"passed_time":0.3535693163,"remaining_time":10.69547182},
{"learn":[0.2995082519],"iteration":32,"passed_time":0.3643685722,"remaining_time":10.67710331},
{"learn":[0.2979367744],"iteration":33,"passed_time":0.3753056609,"remaining_time":10.66309613},
{"learn":[0.2962203738],"iteration":34,"passed_time":0.3871704672,"remaining_time":10.67484288},
{"learn":[0.294641233],"iteration":35,"passed_time":0.3977436302,"remaining_time":10.65069054},
{"learn":[0.2932230457],"iteration":36,"passed_time":0.4080664964,"remaining_time":10.62075773},
{"learn":[0.2920444316],"iteration":37,"passed_time":0.4189164122,"remaining_time":10.6051997},
{"learn":[0.2907423291],"iteration":38,"passed_time":0.4294591834,"remaining_time":10.58231475},
{"learn":[0.2892733569],"iteration":39,"passed_time":0.4405563272,"remaining_time":10.57335185},
{"learn":[0.2882403362],"iteration":40,"passed_time":0.4513179342,"remaining_time":10.55643656},
{"learn":[0.2872223764],"iteration":41,"passed_time":0.4616700111,"remaining_time":10.53047311},
{"learn":[0.2861531596],"iteration":42,"passed_time":0.4720686199,"remaining_time":10.50627138},
{"learn":[0.2851188363],"iteration":43,"passed_time":0.4830415626,"remaining_time":10.49517577},
{"learn":[0.2841289701],"iteration":44,"passed_time":0.493472554,"remaining_time":10.4725842},
{"learn":[0.283057762],"iteration":45,"passed_time":0.5042503104,"remaining_time":10.45771296},
{"learn":[0.2821725348],"iteration":46,"passed_time":0.5150294547,"remaining_time":10.44304405},
{"learn":[0.281340205],"iteration":47,"passed_time":0.5253811583,"remaining_time":10.42005964},
{"learn":[0.2804003224],"iteration":48,"passed_time":0.5361823655,"remaining_time":10.40631489},
{"learn":[0.279686341],"iteration":49,"passed_time":0.5473860121,"remaining_time":10.40033423},
{"learn":[0.2789999371],"iteration":50,"passed_time":0.557639432,"remaining_time":10.37646708},
{"learn":[0.2782851086],"iteration":51,"passed_time":0.5684330183,"remaining_time":10.36297118},
{"learn":[0.2775952133],"iteration":52,"passed_time":0.5794083812,"remaining_time":10.35282523},
{"learn":[0.2769377747],"iteration":53,"passed_time":0.5895315768,"remaining_time":10.32771985},
{"learn":[0.2762614811],"iteration":54,"passed_time":0.6001568366,"remaining_time":10.31178565},
{"learn":[0.2754699448],"iteration":55,"passed_time":0.611589586,"remaining_time":10.30965302},
{"learn":[0.2746927704],"iteration":56,"passed_time":0.6219491778,"remaining_time":10.28943991},
{"learn":[0.2741039737],"iteration":57,"passed_time":0.6328236197,"remaining_time":10.27792844},
{"learn":[0.2735184762],"iteration":58,"passed_time":0.6432020336,"remaining_time":10.25852735},
{"learn":[0.2730456371],"iteration":59,"passed_time":0.6533406183,"remaining_time":10.23566969},
{"learn":[0.2724078659],"iteration":60,"passed_time":0.6643338014,"remaining_time":10.22638425},
{"learn":[0.2718554864],"iteration":61,"passed_time":0.6747574456,"remaining_time":10.20842716},
{"learn":[0.2713687924],"iteration":62,"passed_time":0.6852680143,"remaining_time":10.19200205},
{"learn":[0.2709682887],"iteration":63,"passed_time":0.6960543872,"remaining_time":10.17979541},
{"learn":[0.2704963201],"iteration":64,"passed_time":0.7063961955,"remaining_time":10.16123758},
{"learn":[0.2695548564],"iteration":65,"passed_time":0.7176822874,"remaining_time":10.15629176},
{"learn":[0.2689557916],"iteration":66,"passed_time":0.729322326,"remaining_time":10.15608552},
{"learn":[0.268416128],"iteration":67,"passed_time":0.7417134666,"remaining_time":10.16583751},
{"learn":[0.2680283295],"iteration":68,"passed_time":0.7545490496,"remaining_time":10.18094442},
{"learn":[0.2674824167],"iteration":69,"passed_time":0.7664235997,"remaining_time":10.18248497},
{"learn":[0.2670228586],"iteration":70,"passed_time":0.7789512908,"remaining_time":10.19219365},
{"learn":[0.266493462],"iteration":71,"passed_time":0.7901420784,"remaining_time":10.18405345},
{"learn":[0.2659891279],"iteration":72,"passed_time":0.8014474629,"remaining_time":10.17728491},
{"learn":[0.2656443381],"iteration":73,"passed_time":0.8126902695,"remaining_time":10.16961067},
{"learn":[0.2650896137],"iteration":74,"passed_time":0.8257519116,"remaining_time":10.18427358},
{"learn":[0.2647211923],"iteration":75,"passed_time":0.8362811315,"remaining_time":10.16741797},
{"learn":[0.2642026072],"iteration":76,"passed_time":0.8482055543,"remaining_time":10.167451},
{"learn":[0.2637934442],"iteration":77,"passed_time":0.8592467473,"remaining_time":10.15673719},
{"learn":[0.2634181886],"iteration":78,"passed_time":0.8702448446,"remaining_time":10.14551268},
{"learn":[0.2630793095],"iteration":79,"passed_time":0.8823162434,"remaining_time":10.1466368},
{"learn":[0.2627533046],"iteration":80,"passed_time":0.9065383213,"remaining_time":10.28529281},
{"learn":[0.2624410601],"iteration":81,"passed_time":0.9171568037,"remaining_time":10.26768227},
{"learn":[0.2620255121],"iteration":82,"passed_time":0.9278986017,"remaining_time":10.25160262},
{"learn":[0.2614538272],"iteration":83,"passed_time":0.9386976944,"remaining_time":10.23627486},
{"learn":[0.2608418067],"iteration":84,"passed_time":0.9497505259,"remaining_time":10.22378507},
{"learn":[0.2606045363],"iteration":85,"passed_time":0.9611425648,"remaining_time":10.21493377},
{"learn":[0.2602581091],"iteration":86,"passed_time":0.9732630303,"remaining_time":10.21366835},
{"learn":[0.259810024],"iteration":87,"passed_time":0.9841884175,"remaining_time":10.19977087},
{"learn":[0.2595207635],"iteration":88,"passed_time":0.9953840721,"remaining_time":10.18870663},
{"learn":[0.258985912],"iteration":89,"passed_time":1.007755597,"remaining_time":10.18952882},
{"learn":[0.2587362573],"iteration":90,"passed_time":1.018721801,"remaining_time":10.17602326},
{"learn":[0.2584207199],"iteration":91,"passed_time":1.031115417,"remaining_time":10.17666086},
{"learn":[0.2579025059],"iteration":92,"passed_time":1.043334481,"remaining_time":10.17531585},
{"learn":[0.2577114621],"iteration":93,"passed_time":1.055086497,"remaining_time":10.16923794},
{"learn":[0.2574585917],"iteration":94,"passed_time":1.066644572,"remaining_time":10.16119303},
{"learn":[0.2572351376],"iteration":95,"passed_time":1.079913578,"remaining_time":10.16918619},
{"learn":[0.2569733798],"iteration":96,"passed_time":1.092431426,"remaining_time":10.16974822},
{"learn":[0.2563913858],"iteration":97,"passed_time":1.104242081,"remaining_time":10.16353426},
{"learn":[0.256156071],"iteration":98,"passed_time":1.115105189,"remaining_time":10.14858359},
{"learn":[0.2557227825],"iteration":99,"passed_time":1.127166139,"remaining_time":10.14449525},
{"learn":[0.2554719887],"iteration":100,"passed_time":1.140189447,"remaining_time":10.14881498},
{"learn":[0.255221326],"iteration":101,"passed_time":1.151633472,"remaining_time":10.13889076},
{"learn":[0.2548616632],"iteration":102,"passed_time":1.163221377,"remaining_time":10.13019005},
{"learn":[0.2543100675],"iteration":103,"passed_time":1.175504574,"remaining_time":10.12742402},
{"learn":[0.2538617911],"iteration":104,"passed_time":1.187893694,"remaining_time":10.12537958},
{"learn":[0.253536361],"iteration":105,"passed_time":1.20001633,"remaining_time":10.12089244},
{"learn":[0.2532111297],"iteration":106,"passed_time":1.211965648,"remaining_time":10.11481611},
{"learn":[0.2529369518],"iteration":107,"passed_time":1.223751046,"remaining_time":10.10727716},
{"learn":[0.2526758435],"iteration":108,"passed_time":1.235933448,"remaining_time":10.10290553},
{"learn":[0.2520588472],"iteration":109,"passed_time":1.247304445,"remaining_time":10.09182687},
{"learn":[0.2517414389],"iteration":110,"passed_time":1.25853424,"remaining_time":10.07961207},
{"learn":[0.2515161561],"iteration":111,"passed_time":1.270226605,"remaining_time":10.07108237},
{"learn":[0.2513316246],"iteration":112,"passed_time":1.281120658,"remaining_time":10.0562303},
{"learn":[0.2509309917],"iteration":113,"passed_time":1.292713309,"remaining_time":10.04687712},
{"learn":[0.2504314471],"iteration":114,"passed_time":1.304254716,"remaining_time":10.03709064},
{"learn":[0.250171285],"iteration":115,"passed_time":1.316690272,"remaining_time":10.03408793},
{"learn":[0.2496292103],"iteration":116,"passed_time":1.329287719,"remaining_time":10.03214578},
{"learn":[0.2493137904],"iteration":117,"passed_time":1.341348024,"remaining_time":10.02600811},
{"learn":[0.2490873594],"iteration":118,"passed_time":1.352539537,"remaining_time":10.01333892},
{"learn":[0.2487700204],"iteration":119,"passed_time":1.364435597,"remaining_time":10.00586105},
{"learn":[0.2484268775],"iteration":120,"passed_time":1.375442083,"remaining_time":9.991847858},
{"learn":[0.2478939288],"iteration":121,"passed_time":1.387169409,"remaining_time":9.983071645},
{"learn":[0.2474437434],"iteration":122,"passed_time":1.399599065,"remaining_time":9.979255121},
{"learn":[0.247183621],"iteration":123,"passed_time":1.410719624,"remaining_time":9.966051541},
{"learn":[0.2470212482],"iteration":124,"passed_time":1.42183986,"remaining_time":9.952879019},
{"learn":[0.2465650337],"iteration":125,"passed_time":1.433773407,"remaining_time":9.945380614},
{"learn":[0.2463448393],"iteration":126,"passed_time":1.444502103,"remaining_time":9.929530203},
{"learn":[0.2460151372],"iteration":127,"passed_time":1.455967273,"remaining_time":9.918777049},
{"learn":[0.2458563305],"iteration":128,"passed_time":1.466793928,"remaining_time":9.90370164},
{"learn":[0.2456704444],"iteration":129,"passed_time":1.478760486,"remaining_time":9.896320173},
{"learn":[0.24544412],"iteration":130,"passed_time":1.490472107,"remaining_time":9.887177565},
{"learn":[0.2452420126],"iteration":131,"passed_time":1.502041823,"remaining_time":9.877062899},
{"learn":[0.2450125876],"iteration":132,"passed_time":1.513568331,"remaining_time":9.866644684},
{"learn":[0.2447985841],"iteration":133,"passed_time":1.524902919,"remaining_time":9.854969612},
{"learn":[0.2445118672],"iteration":134,"passed_time":1.536730381,"remaining_time":9.846457623},
{"learn":[0.2441760663],"iteration":135,"passed_time":1.549739326,"remaining_time":9.84540278},
{"learn":[0.2439355723],"iteration":136,"passed_time":1.561360065,"remaining_time":9.835428732},
{"learn":[0.2434825726],"iteration":137,"passed_time":1.573176198,"remaining_time":9.826651326},
{"learn":[0.2432740505],"iteration":138,"passed_time":1.585252408,"remaining_time":9.819441176},
{"learn":[0.2430197867],"iteration":139,"passed_time":1.59634871,"remaining_time":9.806142078},
{"learn":[0.2428756118],"iteration":140,"passed_time":1.607243549,"remaining_time":9.79164687},
{"learn":[0.2424127175],"iteration":141,"passed_time":1.619291053,"remaining_time":9.784167069},
{"learn":[0.2420855196],"iteration":142,"passed_time":1.630882854,"remaining_time":9.773892346},
{"learn":[0.2418423277],"iteration":143,"passed_time":1.641519123,"remaining_time":9.757919234},
{"learn":[0.2416623767],"iteration":144,"passed_time":1.652669563,"remaining_time":9.74505156},
{"learn":[0.2414535754],"iteration":145,"passed_time":1.663732045,"remaining_time":9.731692921},
{"learn":[0.2411350333],"iteration":146,"passed_time":1.674759529,"remaining_time":9.718162434},
{"learn":[0.2409624959],"iteration":147,"passed_time":1.686348114,"remaining_time":9.707895899},
{"learn":[0.2407522323],"iteration":148,"passed_time":1.697637288,"remaining_time":9.695901559},
{"learn":[0.2404699962],"iteration":149,"passed_time":1.708661544,"remaining_time":9.682415417},
{"learn":[0.2402356],"iteration":150,"passed_time":1.71961217,"remaining_time":9.668547896},
{"learn":[0.2398417664],"iteration":151,"passed_time":1.731367282,"remaining_time":9.659206939},
{"learn":[0.2396503676],"iteration":152,"passed_time":1.742882128,"remaining_time":9.648504331},
{"learn":[0.2394574638],"iteration":153,"passed_time":1.753946157,"remaining_time":9.635314602},
{"learn":[0.23910998],"iteration":154,"passed_time":1.765512869,"remaining_time":9.624892736},
{"learn":[0.2388409589],"iteration":155,"passed_time":1.776754053,"remaining_time":9.612695004},
{"learn":[0.2384802669],"iteration":156,"passed_time":1.787875603,"remaining_time":9.599867089},
{"learn":[0.2382146297],"iteration":157,"passed_time":1.798560703,"remaining_time":9.584734885},
{"learn":[0.2379522214],"iteration":158,"passed_time":1.809765268,"remaining_time":9.572406228},
{"learn":[0.2375848849],"iteration":159,"passed_time":1.821081455,"remaining_time":9.560677638},
{"learn":[0.2372632793],"iteration":160,"passed_time":1.835723124,"remaining_time":9.566283859},
{"learn":[0.2368790048],"iteration":161,"passed_time":1.847672583,"remaining_time":9.557713733},
{"learn":[0.2366251519],"iteration":162,"passed_time":1.859083335,"remaining_time":9.546335899},
{"learn":[0.2364542859],"iteration":163,"passed_time":1.869868854,"remaining_time":9.5317705},
{"learn":[0.2363073398],"iteration":164,"passed_time":1.880542103,"remaining_time":9.516682765},
{"learn":[0.2361406203],"iteration":165,"passed_time":1.891538441,"remaining_time":9.503271447},
{"learn":[0.2359455723],"iteration":166,"passed_time":1.902338056,"remaining_time":9.48890779},
{"learn":[0.2357464213],"iteration":167,"passed_time":1.915216733,"remaining_time":9.484882869},
{"learn":[0.2355418313],"iteration":168,"passed_time":1.927851934,"remaining_time":9.479555962},
{"learn":[0.2353181549],"iteration":169,"passed_time":1.938908097,"remaining_time":9.466433652},
{"learn":[0.235049393],"iteration":170,"passed_time":1.950067389,"remaining_time":9.453835472},
{"learn":[0.2347371998],"iteration":171,"passed_time":1.961654901,"remaining_time":9.443315455},
{"learn":[0.2344561783],"iteration":172,"passed_time":1.97270635,"remaining_time":9.430220531},
{"learn":[0.2340640815],"iteration":173,"passed_time":1.983483941,"remaining_time":9.415849055},
{"learn":[0.2338921155],"iteration":174,"passed_time":1.994378902,"remaining_time":9.402071966},
{"learn":[0.2337193936],"iteration":175,"passed_time":2.00617106,"remaining_time":9.392528145},
{"learn":[0.2334103008],"iteration":176,"passed_time":2.01743126,"remaining_time":9.380485464},
{"learn":[0.2331217299],"iteration":177,"passed_time":2.029049771,"remaining_time":9.370106247},
{"learn":[0.2329150957],"iteration":178,"passed_time":2.040685594,"remaining_time":9.359792586},
{"learn":[0.2325664868],"iteration":179,"passed_time":2.051696407,"remaining_time":9.346616963},
{"learn":[0.2324112337],"iteration":180,"passed_time":2.062957757,"remaining_time":9.334598912},
{"learn":[0.2321240377],"iteration":181,"passed_time":2.07486774,"remaining_time":9.32550446},
{"learn":[0.2318762814],"iteration":182,"passed_time":2.08645286,"remaining_time":9.31492889},
{"learn":[0.2317647966],"iteration":183,"passed_time":2.097265878,"remaining_time":9.300918242},
{"learn":[0.2315819979],"iteration":184,"passed_time":2.108711557,"remaining_time":9.289729291},
{"learn":[0.2312525055],"iteration":185,"passed_time":2.120262629,"remaining_time":9.278998818},
{"learn":[0.2310870502],"iteration":186,"passed_time":2.13131309,"remaining_time":9.266083114},
{"learn":[0.2308341434],"iteration":187,"passed_time":2.142713883,"remaining_time":9.254700387},
{"learn":[0.2306277062],"iteration":188,"passed_time":2.153730147,"remaining_time":9.241667458},
{"learn":[0.2305104764],"iteration":189,"passed_time":2.163823689,"remaining_time":9.224722043},
{"learn":[0.2302603889],"iteration":190,"passed_time":2.17453495,"remaining_time":9.210464788},
{"learn":[0.2300074755],"iteration":191,"passed_time":2.18590835,"remaining_time":9.199030971},
{"learn":[0.2297843168],"iteration":192,"passed_time":2.197572363,"remaining_time":9.188812936},
{"learn":[0.2295625304],"iteration":193,"passed_time":2.208603656,"remaining_time":9.175951271},
{"learn":[0.2293230392],"iteration":194,"passed_time":2.219474768,"remaining_time":9.162447118},
{"learn":[0.2291259745],"iteration":195,"passed_time":2.229940748,"remaining_time":9.147307967},
{"learn":[0.2289272942],"iteration":196,"passed_time":2.241041098,"remaining_time":9.134802039},
{"learn":[0.2287685493],"iteration":197,"passed_time":2.252131061,"remaining_time":9.122268235},
{"learn":[0.2284695477],"iteration":198,"passed_time":2.262901843,"remaining_time":9.108464204},
{"learn":[0.2281683148],"iteration":199,"passed_time":2.274026877,"remaining_time":9.096107508},
{"learn":[0.2279727934],"iteration":200,"passed_time":2.285240611,"remaining_time":9.084115662},
{"learn":[0.2277460948],"iteration":201,"passed_time":2.295591837,"remaining_time":9.068724187},
{"learn":[0.2275159899],"iteration":202,"passed_time":2.307049839,"remaining_time":9.057727692},
{"learn":[0.2273976668],"iteration":203,"passed_time":2.318590721,"remaining_time":9.047050067},
{"learn":[0.2271389656],"iteration":204,"passed_time":2.330297634,"remaining_time":9.037007897},
{"learn":[0.2267771809],"iteration":205,"passed_time":2.341399856,"remaining_time":9.024618862},
{"learn":[0.226643623],"iteration":206,"passed_time":2.352553504,"remaining_time":9.012439269},
{"learn":[0.2264624822],"iteration":207,"passed_time":2.363685615,"remaining_time":9.000187535},
{"learn":[0.2262920852],"iteration":208,"passed_time":2.374246655,"remaining_time":8.985785187},
{"learn":[0.2260060131],"iteration":209,"passed_time":2.385919502,"remaining_time":8.975601935},
{"learn":[0.2257837902],"iteration":210,"passed_time":2.396856192,"remaining_time":8.962651825},
{"learn":[0.2255836662],"iteration":211,"passed_time":2.407807609,"remaining_time":8.949775451},
{"learn":[0.2253149404],"iteration":212,"passed_time":2.420648912,"remaining_time":8.943899972},
{"learn":[0.2252381045],"iteration":213,"passed_time":2.431863805,"remaining_time":8.931985752},
{"learn":[0.2251966275],"iteration":214,"passed_time":2.442003351,"remaining_time":8.916151772},
{"learn":[0.2250461762],"iteration":215,"passed_time":2.452967723,"remaining_time":8.903364329},
{"learn":[0.2249430556],"iteration":216,"passed_time":2.46380709,"remaining_time":8.890142633},
{"learn":[0.2247050254],"iteration":217,"passed_time":2.474046167,"remaining_time":8.874789463},
{"learn":[0.2245351914],"iteration":218,"passed_time":2.484697892,"remaining_time":8.860954582},
{"learn":[0.2242964719],"iteration":219,"passed_time":2.495706313,"remaining_time":8.848413293},
{"learn":[0.2239962583],"iteration":220,"passed_time":2.506423411,"remaining_time":8.83485899},
{"learn":[0.2238152248],"iteration":221,"passed_time":2.517135231,"remaining_time":8.821311755},
{"learn":[0.2235560463],"iteration":222,"passed_time":2.530021654,"remaining_time":8.815366929},
{"learn":[0.2233353544],"iteration":223,"passed_time":2.540263793,"remaining_time":8.800199568},
{"learn":[0.2231702325],"iteration":224,"passed_time":2.550946992,"remaining_time":8.786595195},
{"learn":[0.2228646975],"iteration":225,"passed_time":2.562378876,"remaining_time":8.775580754},
{"learn":[0.2224713865],"iteration":226,"passed_time":2.573122769,"remaining_time":8.762219824},
{"learn":[0.2223560606],"iteration":227,"passed_time":2.583757244,"remaining_time":8.748511371},
{"learn":[0.2221101219],"iteration":228,"passed_time":2.594859129,"remaining_time":8.736403443},
{"learn":[0.2218367661],"iteration":229,"passed_time":2.605581035,"remaining_time":8.723032162},
{"learn":[0.2216836723],"iteration":230,"passed_time":2.616459287,"remaining_time":8.710204294},
{"learn":[0.2214649231],"iteration":231,"passed_time":2.627841667,"remaining_time":8.699062069},
{"learn":[0.2213042306],"iteration":232,"passed_time":2.638307218,"remaining_time":8.684899727},
{"learn":[0.2210970942],"iteration":233,"passed_time":2.649295126,"remaining_time":8.672478915},
{"learn":[0.2208256254],"iteration":234,"passed_time":2.660646604,"remaining_time":8.661253838},
{"learn":[0.2205690785],"iteration":235,"passed_time":2.67138199,"remaining_time":8.648033222},
{"learn":[0.2205301494],"iteration":236,"passed_time":2.681870982,"remaining_time":8.634040335},
{"learn":[0.2202909232],"iteration":237,"passed_time":2.693007888,"remaining_time":8.622151304},
{"learn":[0.2200538788],"iteration":238,"passed_time":2.703687934,"remaining_time":8.608813881},
{"learn":[0.2199095118],"iteration":239,"passed_time":2.715694346,"remaining_time":8.599698762},
{"learn":[0.2197466601],"iteration":240,"passed_time":2.726503029,"remaining_time":8.586787548},
{"learn":[0.2195329561],"iteration":241,"passed_time":2.737230464,"remaining_time":8.57363922},
{"learn":[0.2194310589],"iteration":242,"passed_time":2.747813044,"remaining_time":8.560059564},
{"learn":[0.2192820693],"iteration":243,"passed_time":2.759053321,"remaining_time":8.548542258},
{"learn":[0.2190907039],"iteration":244,"passed_time":2.769743101,"remaining_time":8.535330781},
{"learn":[0.2188140798],"iteration":245,"passed_time":2.780594551,"remaining_time":8.522635331},
{"learn":[0.2187723937],"iteration":246,"passed_time":2.791385897,"remaining_time":8.50977158},
{"learn":[0.218580389],"iteration":247,"passed_time":2.801591858,"remaining_time":8.495149505},
{"learn":[0.2183502217],"iteration":248,"passed_time":2.812606974,"remaining_time":8.483003364},
{"learn":[0.2182339679],"iteration":249,"passed_time":2.823010194,"remaining_time":8.469030582},
{"learn":[0.2180953682],"iteration":250,"passed_time":2.833453295,"remaining_time":8.455205252},
{"learn":[0.2178637507],"iteration":251,"passed_time":2.844355683,"remaining_time":8.442770044},
{"learn":[0.217687515],"iteration":252,"passed_time":2.854756476,"remaining_time":8.428865958},
{"learn":[0.2175697378],"iteration":253,"passed_time":2.865379353,"remaining_time":8.415641723},
{"learn":[0.2175407685],"iteration":254,"passed_time":2.875629404,"remaining_time":8.401348651},
{"learn":[0.2174077707],"iteration":255,"passed_time":2.885638675,"remaining_time":8.3863874},
{"learn":[0.2172955472],"iteration":256,"passed_time":2.896269774,"remaining_time":8.37326242},
{"learn":[0.2170678806],"iteration":257,"passed_time":2.907248605,"remaining_time":8.361156839},
{"learn":[0.2168990205],"iteration":258,"passed_time":2.917549368,"remaining_time":8.347120005},
{"learn":[0.216667716],"iteration":259,"passed_time":2.928641576,"remaining_time":8.335364486},
{"learn":[0.2164857882],"iteration":260,"passed_time":2.939579183,"remaining_time":8.323176308},
{"learn":[0.2162253393],"iteration":261,"passed_time":2.950041417,"remaining_time":8.309658648},
{"learn":[0.2161009835],"iteration":262,"passed_time":2.960741906,"remaining_time":8.296831881},
{"learn":[0.2160741933],"iteration":263,"passed_time":2.971167194,"remaining_time":8.283253996},
{"learn":[0.2159651083],"iteration":264,"passed_time":2.981421215,"remaining_time":8.26922488},
{"learn":[0.2157781296],"iteration":265,"passed_time":2.993237108,"remaining_time":8.259533975},
{"learn":[0.2156340404],"iteration":266,"passed_time":3.004966664,"remaining_time":8.249590129},
{"learn":[0.2155115667],"iteration":267,"passed_time":3.016218876,"remaining_time":8.238329169},
{"learn":[0.2153540862],"iteration":268,"passed_time":3.027862441,"remaining_time":8.228131764},
{"learn":[0.2151683069],"iteration":269,"passed_time":3.03943404,"remaining_time":8.21772907},
{"learn":[0.2149896685],"iteration":270,"passed_time":3.050385724,"remaining_time":8.205650157},
{"learn":[0.214745504],"iteration":271,"passed_time":3.061060565,"remaining_time":8.19283857},
{"learn":[0.2146061318],"iteration":272,"passed_time":3.071638904,"remaining_time":8.179785652},
{"learn":[0.214454087],"iteration":273,"passed_time":3.081820183,"remaining_time":8.165698733},
{"learn":[0.2143165752],"iteration":274,"passed_time":3.092467877,"remaining_time":8.152869857},
{"learn":[0.2141063941],"iteration":275,"passed_time":3.103205787,"remaining_time":8.140293442},
{"learn":[0.2138768702],"iteration":276,"passed_time":3.114754216,"remaining_time":8.129845842},
{"learn":[0.2138238669],"iteration":277,"passed_time":3.125523503,"remaining_time":8.117366795},
{"learn":[0.2136089861],"iteration":278,"passed_time":3.136350362,"remaining_time":8.105048786},
{"learn":[0.2134129106],"iteration":279,"passed_time":3.153262526,"remaining_time":8.108389352},
{"learn":[0.2132277541],"iteration":280,"passed_time":3.163428368,"remaining_time":8.094323831},
{"learn":[0.212995862],"iteration":281,"passed_time":3.174762642,"remaining_time":8.083260911},
{"learn":[0.2127270703],"iteration":282,"passed_time":3.185688906,"remaining_time":8.071162351},
{"learn":[0.2125263699],"iteration":283,"passed_time":3.196090544,"remaining_time":8.057749399},
{"learn":[0.2123596314],"iteration":284,"passed_time":3.207048093,"remaining_time":8.045752234},
{"learn":[0.2122086368],"iteration":285,"passed_time":3.218292568,"remaining_time":8.034478649},
{"learn":[0.2120432565],"iteration":286,"passed_time":3.228816366,"remaining_time":8.021414873},
{"learn":[0.2119856676],"iteration":287,"passed_time":3.239221846,"remaining_time":8.00807623},
{"learn":[0.2118360871],"iteration":288,"passed_time":3.250579115,"remaining_time":7.997099485},
{"learn":[0.2116147793],"iteration":289,"passed_time":3.261301397,"remaining_time":7.984565488},
{"learn":[0.2114069967],"iteration":290,"passed_time":3.272224121,"remaining_time":7.97253231},
{"learn":[0.2113787046],"iteration":291,"passed_time":3.282580493,"remaining_time":7.959133524},
{"learn":[0.2112771343],"iteration":292,"passed_time":3.292770559,"remaining_time":7.945354215},
{"learn":[0.2111965466],"iteration":293,"passed_time":3.303372953,"remaining_time":7.932589471},
{"learn":[0.2110714638],"iteration":294,"passed_time":3.314224299,"remaining_time":7.920434342},
{"learn":[0.2108611516],"iteration":295,"passed_time":3.324828363,"remaining_time":7.907699891},
{"learn":[0.2106996269],"iteration":296,"passed_time":3.335635838,"remaining_time":7.895461259},
{"learn":[0.210588646],"iteration":297,"passed_time":3.346313762,"remaining_time":7.882927051},
{"learn":[0.2104448391],"iteration":298,"passed_time":3.357391029,"remaining_time":7.87134151},
{"learn":[0.2103184503],"iteration":299,"passed_time":3.368197509,"remaining_time":7.859127521},
{"learn":[0.2101713725],"iteration":300,"passed_time":3.378454211,"remaining_time":7.845646158},
{"learn":[0.2099751889],"iteration":301,"passed_time":3.389582612,"remaining_time":7.834200871},
{"learn":[0.2099516541],"iteration":302,"passed_time":3.399831955,"remaining_time":7.820735554},
{"learn":[0.2097163734],"iteration":303,"passed_time":3.410622501,"remaining_time":7.808530462},
{"learn":[0.2095408485],"iteration":304,"passed_time":3.42173505,"remaining_time":7.797068393},
{"learn":[0.2093996863],"iteration":305,"passed_time":3.432502516,"remaining_time":7.784825969},
{"learn":[0.2093583422],"iteration":306,"passed_time":3.442364006,"remaining_time":7.770548065},
{"learn":[0.2092269235],"iteration":307,"passed_time":3.45286079,"remaining_time":7.757726191},
{"learn":[0.2091325072],"iteration":308,"passed_time":3.463777711,"remaining_time":7.745858895},
{"learn":[0.2090208277],"iteration":309,"passed_time":3.474030776,"remaining_time":7.732520114},
{"learn":[0.2088211895],"iteration":310,"passed_time":3.485332777,"remaining_time":7.721525026},
{"learn":[0.2086961889],"iteration":311,"passed_time":3.496255567,"remaining_time":7.709691762},
{"learn":[0.2086583369],"iteration":312,"passed_time":3.507322626,"remaining_time":7.69818097},
{"learn":[0.2084782754],"iteration":313,"passed_time":3.51847338,"remaining_time":7.686855855},
{"learn":[0.2083690825],"iteration":314,"passed_time":3.52919729,"remaining_time":7.674603631},
{"learn":[0.2081396936],"iteration":315,"passed_time":3.539779163,"remaining_time":7.662053631},
{"learn":[0.2079979378],"iteration":316,"passed_time":3.550581789,"remaining_time":7.649991678},
{"learn":[0.2078480191],"iteration":317,"passed_time":3.561957798,"remaining_time":7.639167352},
{"learn":[0.2076712445],"iteration":318,"passed_time":3.572526049,"remaining_time":7.626615171},
{"learn":[0.2075951796],"iteration":319,"passed_time":3.583246382,"remaining_time":7.614398562},
{"learn":[0.2074421288],"iteration":320,"passed_time":3.59403663,"remaining_time":7.602339165},
{"learn":[0.2073182912],"iteration":321,"passed_time":3.604748197,"remaining_time":7.590121981},
{"learn":[0.2072917457],"iteration":322,"passed_time":3.61504663,"remaining_time":7.5770482},
{"learn":[0.2071722743],"iteration":323,"passed_time":3.62541921,"remaining_time":7.564146252},
{"learn":[0.2070481818],"iteration":324,"passed_time":3.635978912,"remaining_time":7.55164851},
{"learn":[0.2068463182],"iteration":325,"passed_time":3.648302887,"remaining_time":7.542810263},
{"learn":[0.2066979281],"iteration":326,"passed_time":3.659669363,"remaining_time":7.531980065},
{"learn":[0.2065751609],"iteration":327,"passed_time":3.670417712,"remaining_time":7.519880191},
{"learn":[0.2064053006],"iteration":328,"passed_time":3.681600738,"remaining_time":7.508675061},
{"learn":[0.2062430078],"iteration":329,"passed_time":3.693073927,"remaining_time":7.498059185},
{"learn":[0.2061219335],"iteration":330,"passed_time":3.704060169,"remaining_time":7.486453937},
{"learn":[0.2060272833],"iteration":331,"passed_time":3.714605131,"remaining_time":7.473964541},
{"learn":[0.2059386679],"iteration":332,"passed_time":3.725586886,"remaining_time":7.46236172},
{"learn":[0.2057676059],"iteration":333,"passed_time":3.736020257,"remaining_time":7.449669136},
{"learn":[0.2057429216],"iteration":334,"passed_time":3.746492723,"remaining_time":7.437067643},
{"learn":[0.2055743352],"iteration":335,"passed_time":3.758673402,"remaining_time":7.42785458},
{"learn":[0.2054666347],"iteration":336,"passed_time":3.769269985,"remaining_time":7.415507418},
{"learn":[0.2052977381],"iteration":337,"passed_time":3.780774452,"remaining_time":7.404948778},
{"learn":[0.2052212852],"iteration":338,"passed_time":3.79188908,"remaining_time":7.393624431},
{"learn":[0.2050722958],"iteration":339,"passed_time":3.802168638,"remaining_time":7.380680297},
{"learn":[0.2049333426],"iteration":340,"passed_time":3.813229055,"remaining_time":7.369260842},
{"learn":[0.2048287148],"iteration":341,"passed_time":3.824047093,"remaining_time":7.357377156},
{"learn":[0.2046174558],"iteration":342,"passed_time":3.835723894,"remaining_time":7.347144601},
{"learn":[0.2044745756],"iteration":343,"passed_time":3.846512209,"remaining_time":7.335209329},
{"learn":[0.20432924],"iteration":344,"passed_time":3.857514855,"remaining_time":7.323687623},
{"learn":[0.2042065324],"iteration":345,"passed_time":3.868935994,"remaining_time":7.312959943},
{"learn":[0.2041828938],"iteration":346,"passed_time":3.879189363,"remaining_time":7.300030704},
{"learn":[0.2040778744],"iteration":347,"passed_time":3.890331359,"remaining_time":7.288781741},
{"learn":[0.2039335555],"iteration":348,"passed_time":3.901297693,"remaining_time":7.277205726},
{"learn":[0.2038562588],"iteration":349,"passed_time":3.911833951,"remaining_time":7.264834481},
{"learn":[0.2037491898],"iteration":350,"passed_time":3.92300798,"remaining_time":7.253652932},
{"learn":[0.20354042],"iteration":351,"passed_time":3.933215409,"remaining_time":7.240692003},
{"learn":[0.2034252881],"iteration":352,"passed_time":3.9440672,"remaining_time":7.228927701},
{"learn":[0.2031753602],"iteration":353,"passed_time":3.955560236,"remaining_time":7.218338736},
{"learn":[0.2030436698],"iteration":354,"passed_time":3.966032323,"remaining_time":7.205889714},
{"learn":[0.202896436],"iteration":355,"passed_time":3.977207822,"remaining_time":7.194724262},
{"learn":[0.2027739397],"iteration":356,"passed_time":3.988391139,"remaining_time":7.183572835},
{"learn":[0.2026869658],"iteration":357,"passed_time":3.998724329,"remaining_time":7.170896701},
{"learn":[0.2025879822],"iteration":358,"passed_time":4.00941184,"remaining_time":7.158866265},
{"learn":[0.2024348028],"iteration":359,"passed_time":4.020653818,"remaining_time":7.14782901},
{"learn":[0.2023382096],"iteration":360,"passed_time":4.031009155,"remaining_time":7.135221191},
{"learn":[0.2022128316],"iteration":361,"passed_time":4.04190655,"remaining_time":7.123581158},
{"learn":[0.2021348899],"iteration":362,"passed_time":4.053092601,"remaining_time":7.112451755},
{"learn":[0.2021115724],"iteration":363,"passed_time":4.063246991,"remaining_time":7.099519468},
{"learn":[0.2020987018],"iteration":364,"passed_time":4.07349214,"remaining_time":7.086760298},
{"learn":[0.2020197081],"iteration":365,"passed_time":4.083809373,"remaining_time":7.074139734},
{"learn":[0.201854512],"iteration":366,"passed_time":4.094301888,"remaining_time":7.061834047},
{"learn":[0.201778598],"iteration":367,"passed_time":4.105122866,"remaining_time":7.050102313},
{"learn":[0.2016720309],"iteration":368,"passed_time":4.115481883,"remaining_time":7.037585551},
{"learn":[0.2015680928],"iteration":369,"passed_time":4.126406765,"remaining_time":7.026043951},
{"learn":[0.2013871243],"iteration":370,"passed_time":4.137126923,"remaining_time":7.014158584},
{"learn":[0.2012046007],"iteration":371,"passed_time":4.147808668,"remaining_time":7.002214633},
{"learn":[0.2011084685],"iteration":372,"passed_time":4.157943697,"remaining_time":6.98935844},
{"learn":[0.201007214],"iteration":373,"passed_time":4.16855354,"remaining_time":6.977311539},
{"learn":[0.200884061],"iteration":374,"passed_time":4.17905395,"remaining_time":6.965089917},
{"learn":[0.2008012054],"iteration":375,"passed_time":4.189822165,"remaining_time":6.953321891},
{"learn":[0.20060811],"iteration":376,"passed_time":4.200919353,"remaining_time":6.942102804},
{"learn":[0.2005217774],"iteration":377,"passed_time":4.21132448,"remaining_time":6.929745572},
{"learn":[0.2004164274],"iteration":378,"passed_time":4.222213857,"remaining_time":6.918192099},
{"learn":[0.2002655145],"iteration":379,"passed_time":4.233158245,"remaining_time":6.906731873},
{"learn":[0.2001825683],"iteration":380,"passed_time":4.243257461,"remaining_time":6.893901229},
{"learn":[0.2000401375],"iteration":381,"passed_time":4.254141352,"remaining_time":6.882354334},
{"learn":[0.2000161698],"iteration":382,"passed_time":4.263850827,"remaining_time":6.868918956},
{"learn":[0.1999154125],"iteration":383,"passed_time":4.274295792,"remaining_time":6.856682832},
{"learn":[0.1998197326],"iteration":384,"passed_time":4.285991475,"remaining_time":6.846453914},
{"learn":[0.1996960522],"iteration":385,"passed_time":4.29716999,"remaining_time":6.835394751},
{"learn":[0.1996771493],"iteration":386,"passed_time":4.307214039,"remaining_time":6.822537999},
{"learn":[0.1996062371],"iteration":387,"passed_time":4.318172549,"remaining_time":6.811138145},
{"learn":[0.1995764493],"iteration":388,"passed_time":4.328492547,"remaining_time":6.798737651},
{"learn":[0.1994568676],"iteration":389,"passed_time":4.339191223,"remaining_time":6.786940118},
{"learn":[0.1993775573],"iteration":390,"passed_time":4.350251618,"remaining_time":6.775711599},
{"learn":[0.1992243981],"iteration":391,"passed_time":4.360946428,"remaining_time":6.763916908},
{"learn":[0.1991282571],"iteration":392,"passed_time":4.371231529,"remaining_time":6.751495009},
{"learn":[0.1990075517],"iteration":393,"passed_time":4.382179496,"remaining_time":6.740103489},
{"learn":[0.1989275272],"iteration":394,"passed_time":4.392484672,"remaining_time":6.727729688},
{"learn":[0.1989164152],"iteration":395,"passed_time":4.402712997,"remaining_time":6.715249117},
{"learn":[0.1987721914],"iteration":396,"passed_time":4.413708654,"remaining_time":6.703945386},
{"learn":[0.1986504641],"iteration":397,"passed_time":4.424189288,"remaining_time":6.691864199},
{"learn":[0.198542957],"iteration":398,"passed_time":4.434862278,"remaining_time":6.680080775},
{"learn":[0.1983919623],"iteration":399,"passed_time":4.44571182,"remaining_time":6.668567731},
{"learn":[0.1981784719],"iteration":400,"passed_time":4.456455442,"remaining_time":6.656899774},
{"learn":[0.1980502874],"iteration":401,"passed_time":4.467552714,"remaining_time":6.645762494},
{"learn":[0.1979738707],"iteration":402,"passed_time":4.478178258,"remaining_time":6.633926601},
{"learn":[0.1978880641],"iteration":403,"passed_time":4.489709104,"remaining_time":6.623432242},
{"learn":[0.1978118942],"iteration":404,"passed_time":4.500514363,"remaining_time":6.611866779},
{"learn":[0.1977014583],"iteration":405,"passed_time":4.511090921,"remaining_time":6.59997046},
{"learn":[0.1975807185],"iteration":406,"passed_time":4.521613185,"remaining_time":6.58800152},
{"learn":[0.1974255959],"iteration":407,"passed_time":4.532508142,"remaining_time":6.576580442},
{"learn":[0.1972710205],"iteration":408,"passed_time":4.54352783,"remaining_time":6.56534217},
{"learn":[0.1971915164],"iteration":409,"passed_time":4.553719463,"remaining_time":6.552913374},
{"learn":[0.1970612288],"iteration":410,"passed_time":4.56483141,"remaining_time":6.541814356},
{"learn":[0.1969467007],"iteration":411,"passed_time":4.575940966,"remaining_time":6.530711864},
{"learn":[0.1969357648],"iteration":412,"passed_time":4.585798919,"remaining_time":6.517830425},
{"learn":[0.1968054132],"iteration":413,"passed_time":4.59674843,"remaining_time":6.506508648},
{"learn":[0.1967017115],"iteration":414,"passed_time":4.607006062,"remaining_time":6.494213364},
{"learn":[0.1965883519],"iteration":415,"passed_time":4.617376995,"remaining_time":6.482086935},
{"learn":[0.1964777012],"iteration":416,"passed_time":4.62856372,"remaining_time":6.471109469},
{"learn":[0.1962229904],"iteration":417,"passed_time":4.639354693,"remaining_time":6.459579979},
{"learn":[0.1961965731],"iteration":418,"passed_time":4.649514007,"remaining_time":6.447178133},
{"learn":[0.1961780573],"iteration":419,"passed_time":4.659992221,"remaining_time":6.435227353},
{"learn":[0.1961119293],"iteration":420,"passed_time":4.670100816,"remaining_time":6.422775232},
{"learn":[0.1959767243],"iteration":421,"passed_time":4.681799,"remaining_time":6.412511427},
{"learn":[0.1958846437],"iteration":422,"passed_time":4.692321183,"remaining_time":6.400636696},
{"learn":[0.1957599535],"iteration":423,"passed_time":4.702811348,"remaining_time":6.388724851},
{"learn":[0.1956446936],"iteration":424,"passed_time":4.713237155,"remaining_time":6.376732621},
{"learn":[0.1955536714],"iteration":425,"passed_time":4.724219804,"remaining_time":6.365498046},
{"learn":[0.1954126583],"iteration":426,"passed_time":4.735206397,"remaining_time":6.354269943},
{"learn":[0.1953293932],"iteration":427,"passed_time":4.745884885,"remaining_time":6.342631201},
{"learn":[0.1951846836],"iteration":428,"passed_time":4.757222024,"remaining_time":6.331873603},
{"learn":[0.1950422212],"iteration":429,"passed_time":4.767831922,"remaining_time":6.320149292},
{"learn":[0.1949482028],"iteration":430,"passed_time":4.779235353,"remaining_time":6.309477763},
{"learn":[0.1949343702],"iteration":431,"passed_time":4.789892839,"remaining_time":6.297822067},
{"learn":[0.1947988224],"iteration":432,"passed_time":4.800395546,"remaining_time":6.285968301},
{"learn":[0.1946488294],"iteration":433,"passed_time":4.811723709,"remaining_time":6.27519728},
{"learn":[0.1945654058],"iteration":434,"passed_time":4.822543055,"remaining_time":6.263762819},
{"learn":[0.1945555698],"iteration":435,"passed_time":4.832322589,"remaining_time":6.250986102},
{"learn":[0.1944592592],"iteration":436,"passed_time":4.843116526,"remaining_time":6.239529986},
{"learn":[0.1944454857],"iteration":437,"passed_time":4.853097528,"remaining_time":6.227033815},
{"learn":[0.1942868807],"iteration":438,"passed_time":4.863907828,"remaining_time":6.215608865},
{"learn":[0.1941808071],"iteration":439,"passed_time":4.874845426,"remaining_time":6.204348724},
{"learn":[0.1941726616],"iteration":440,"passed_time":4.884869887,"remaining_time":6.191932578},
{"learn":[0.1941003782],"iteration":441,"passed_time":4.895927939,"remaining_time":6.180832104},
{"learn":[0.1940133762],"iteration":442,"passed_time":4.906790923,"remaining_time":6.169486555},
{"learn":[0.1938616437],"iteration":443,"passed_time":4.917399173,"remaining_time":6.15782419},
{"learn":[0.1937040074],"iteration":444,"passed_time":4.927940524,"remaining_time":6.146083125},
{"learn":[0.1936142935],"iteration":445,"passed_time":4.939034338,"remaining_time":6.135033684},
{"learn":[0.1935337584],"iteration":446,"passed_time":4.949167315,"remaining_time":6.122795359},
{"learn":[0.1934423125],"iteration":447,"passed_time":4.960797755,"remaining_time":6.112411519},
{"learn":[0.1933555049],"iteration":448,"passed_time":4.972048902,"remaining_time":6.101556671},
{"learn":[0.1933001358],"iteration":449,"passed_time":4.98308504,"remaining_time":6.090437271},
{"learn":[0.193135658],"iteration":450,"passed_time":4.994830732,"remaining_time":6.080181978},
{"learn":[0.1930526434],"iteration":451,"passed_time":5.00681923,"remaining_time":6.070214465},
{"learn":[0.1929117319],"iteration":452,"passed_time":5.018407298,"remaining_time":6.059754507},
{"learn":[0.1928356786],"iteration":453,"passed_time":5.028667899,"remaining_time":6.047693112},
{"learn":[0.1927222756],"iteration":454,"passed_time":5.059520188,"remaining_time":6.060304401},
{"learn":[0.1927105159],"iteration":455,"passed_time":5.074814253,"remaining_time":6.054164372},
{"learn":[0.1926169696],"iteration":456,"passed_time":5.086423987,"remaining_time":6.043606619},
{"learn":[0.1925259207],"iteration":457,"passed_time":5.096689285,"remaining_time":6.031453259},
{"learn":[0.1924023205],"iteration":458,"passed_time":5.107406848,"remaining_time":6.019841187},
{"learn":[0.1922910866],"iteration":459,"passed_time":5.11849304,"remaining_time":6.008665742},
{"learn":[0.1921984877],"iteration":460,"passed_time":5.129186792,"remaining_time":5.997031846},
{"learn":[0.192162405],"iteration":461,"passed_time":5.139181077,"remaining_time":5.984587488},
{"learn":[0.1919648512],"iteration":462,"passed_time":5.150502891,"remaining_time":5.973693418},
{"learn":[0.1918009945],"iteration":463,"passed_time":5.161011673,"remaining_time":5.961858312},
{"learn":[0.1917165254],"iteration":464,"passed_time":5.172016277,"remaining_time":5.950599372},
{"learn":[0.1915604715],"iteration":465,"passed_time":5.183371189,"remaining_time":5.93974295},
{"learn":[0.1914618766],"iteration":466,"passed_time":5.193851804,"remaining_time":5.927886534},
{"learn":[0.1913639599],"iteration":467,"passed_time":5.20560107,"remaining_time":5.91747814},
{"learn":[0.1913252559],"iteration":468,"passed_time":5.216306435,"remaining_time":5.905882126},
{"learn":[0.1913016883],"iteration":469,"passed_time":5.226508448,"remaining_time":5.893722292},
{"learn":[0.1912165946],"iteration":470,"passed_time":5.237867647,"remaining_time":5.882870457},
{"learn":[0.1911524343],"iteration":471,"passed_time":5.24870671,"remaining_time":5.871434625},
{"learn":[0.1909821795],"iteration":472,"passed_time":5.259425953,"remaining_time":5.859867817},
{"learn":[0.1909744792],"iteration":473,"passed_time":5.270091219,"remaining_time":5.848244686},
{"learn":[0.1909286864],"iteration":474,"passed_time":5.280890375,"remaining_time":5.836773572},
{"learn":[0.1908855308],"iteration":475,"passed_time":5.291271202,"remaining_time":5.824844769},
{"learn":[0.190802685],"iteration":476,"passed_time":5.301982854,"remaining_time":5.813285183},
{"learn":[0.1907953717],"iteration":477,"passed_time":5.312479023,"remaining_time":5.801493829},
{"learn":[0.1907049519],"iteration":478,"passed_time":5.322957195,"remaining_time":5.789688306},
{"learn":[0.1906980138],"iteration":479,"passed_time":5.333420686,"remaining_time":5.77787241},
{"learn":[0.1906708094],"iteration":480,"passed_time":5.343603219,"remaining_time":5.765758982},
{"learn":[0.1904797567],"iteration":481,"passed_time":5.354507113,"remaining_time":5.754428806},
{"learn":[0.1903214759],"iteration":482,"passed_time":5.365344352,"remaining_time":5.743029047},
{"learn":[0.1902184865],"iteration":483,"passed_time":5.375801454,"remaining_time":5.731226343},
{"learn":[0.190116087],"iteration":484,"passed_time":5.38638772,"remaining_time":5.719566342},
{"learn":[0.1900052851],"iteration":485,"passed_time":5.397203765,"remaining_time":5.708153776},
{"learn":[0.1898291193],"iteration":486,"passed_time":5.407866909,"remaining_time":5.696582596},
{"learn":[0.1897013581],"iteration":487,"passed_time":5.418728421,"remaining_time":5.685223261},
{"learn":[0.1896359386],"iteration":488,"passed_time":5.429366048,"remaining_time":5.673632006},
{"learn":[0.1895328473],"iteration":489,"passed_time":5.439542079,"remaining_time":5.661564204},
{"learn":[0.1894217873],"iteration":490,"passed_time":5.450255812,"remaining_time":5.650061524},
{"learn":[0.1893575543],"iteration":491,"passed_time":5.462378837,"remaining_time":5.640017174},
{"learn":[0.1892881598],"iteration":492,"passed_time":5.474505264,"remaining_time":5.629967888},
{"learn":[0.1892805561],"iteration":493,"passed_time":5.48472218,"remaining_time":5.617954298},
{"learn":[0.1891617158],"iteration":494,"passed_time":5.495818161,"remaining_time":5.60684479},
{"learn":[0.1890574803],"iteration":495,"passed_time":5.506554899,"remaining_time":5.595370301},
{"learn":[0.1889684672],"iteration":496,"passed_time":5.517221578,"remaining_time":5.583827874},
{"learn":[0.1888971655],"iteration":497,"passed_time":5.52809026,"remaining_time":5.572492591},
{"learn":[0.1887780849],"iteration":498,"passed_time":5.538407885,"remaining_time":5.560605913},
{"learn":[0.1886925237],"iteration":499,"passed_time":5.548969249,"remaining_time":5.548969249},
{"learn":[0.1886195678],"iteration":500,"passed_time":5.559866432,"remaining_time":5.537671356},
{"learn":[0.1885087662],"iteration":501,"passed_time":5.570061237,"remaining_time":5.525678279},
{"learn":[0.1883334093],"iteration":502,"passed_time":5.581106928,"remaining_time":5.514533088},
{"learn":[0.188247246],"iteration":503,"passed_time":5.592304938,"remaining_time":5.503538193},
{"learn":[0.1881219035],"iteration":504,"passed_time":5.602862531,"remaining_time":5.491914758},
{"learn":[0.1880519763],"iteration":505,"passed_time":5.614018147,"remaining_time":5.480879376},
{"learn":[0.1879985494],"iteration":506,"passed_time":5.624838202,"remaining_time":5.469517226},
{"learn":[0.187891029],"iteration":507,"passed_time":5.635110658,"remaining_time":5.457626858},
{"learn":[0.1877861165],"iteration":508,"passed_time":5.645879338,"remaining_time":5.446221523},
{"learn":[0.1877783677],"iteration":509,"passed_time":5.65661841,"remaining_time":5.434790237},
{"learn":[0.1877195207],"iteration":510,"passed_time":5.667104444,"remaining_time":5.423119517},
{"learn":[0.1876297533],"iteration":511,"passed_time":5.67789177,"remaining_time":5.411740593},
{"learn":[0.1875545056],"iteration":512,"passed_time":5.688517137,"remaining_time":5.400210226},
{"learn":[0.1874759401],"iteration":513,"passed_time":5.698898981,"remaining_time":5.388453122},
{"learn":[0.1874129834],"iteration":514,"passed_time":5.710060002,"remaining_time":5.377435148},
{"learn":[0.1873120864],"iteration":515,"passed_time":5.721226224,"remaining_time":5.366421497},
{"learn":[0.1872185374],"iteration":516,"passed_time":5.732110472,"remaining_time":5.355143826},
{"learn":[0.187089924],"iteration":517,"passed_time":5.743139726,"remaining_time":5.344002602},
{"learn":[0.18708328],"iteration":518,"passed_time":5.7532646,"remaining_time":5.332023647},
{"learn":[0.1870257935],"iteration":519,"passed_time":5.763815567,"remaining_time":5.320445139},
{"learn":[0.1869649656],"iteration":520,"passed_time":5.774491121,"remaining_time":5.308985119},
{"learn":[0.1869017243],"iteration":521,"passed_time":5.784476884,"remaining_time":5.296896457},
{"learn":[0.1868081878],"iteration":522,"passed_time":5.795133918,"remaining_time":5.285428066},
{"learn":[0.1866723645],"iteration":523,"passed_time":5.806686861,"remaining_time":5.274776614},
{"learn":[0.1866678579],"iteration":524,"passed_time":5.816327724,"remaining_time":5.26239175},
{"learn":[0.1866148506],"iteration":525,"passed_time":5.827217745,"remaining_time":5.251142987},
{"learn":[0.1865589235],"iteration":526,"passed_time":5.838081031,"remaining_time":5.239871589},
{"learn":[0.186511955],"iteration":527,"passed_time":5.84808072,"remaining_time":5.227829734},
{"learn":[0.1864397041],"iteration":528,"passed_time":5.860243354,"remaining_time":5.217721399},
{"learn":[0.1863866348],"iteration":529,"passed_time":5.871574373,"remaining_time":5.20686784},
{"learn":[0.1862332767],"iteration":530,"passed_time":5.882176078,"remaining_time":5.195368325},
{"learn":[0.1861593915],"iteration":531,"passed_time":5.892808163,"remaining_time":5.18389891},
{"learn":[0.1860910598],"iteration":532,"passed_time":5.903899238,"remaining_time":5.172834792},
{"learn":[0.1859974075],"iteration":533,"passed_time":5.914269478,"remaining_time":5.161141529},
{"learn":[0.1859067676],"iteration":534,"passed_time":5.925382364,"remaining_time":5.150098691},
{"learn":[0.1858583242],"iteration":535,"passed_time":5.936249027,"remaining_time":5.138842442},
{"learn":[0.1857668046],"iteration":536,"passed_time":5.947040113,"remaining_time":5.127522481},
{"learn":[0.1857190363],"iteration":537,"passed_time":5.957554879,"remaining_time":5.115967201},
{"learn":[0.1857042309],"iteration":538,"passed_time":5.968250909,"remaining_time":5.104570815},
{"learn":[0.1855968086],"iteration":539,"passed_time":5.97859829,"remaining_time":5.092880025},
{"learn":[0.1855145996],"iteration":540,"passed_time":5.989724205,"remaining_time":5.081854732},
{"learn":[0.1853951111],"iteration":541,"passed_time":6.001607059,"remaining_time":5.071468695},
{"learn":[0.185388848],"iteration":542,"passed_time":6.011408034,"remaining_time":5.059324994},
{"learn":[0.1853142493],"iteration":543,"passed_time":6.022011972,"remaining_time":5.047862977},
{"learn":[0.1852232502],"iteration":544,"passed_time":6.032851645,"remaining_time":5.036600914},
{"learn":[0.1850572811],"iteration":545,"passed_time":6.043601754,"remaining_time":5.025265927},
{"learn":[0.185052927],"iteration":546,"passed_time":6.053985969,"remaining_time":5.013630062},
{"learn":[0.1848855615],"iteration":547,"passed_time":6.064841174,"remaining_time":5.002387246},
{"learn":[0.1848154127],"iteration":548,"passed_time":6.075513903,"remaining_time":4.990995938},
{"learn":[0.1847276841],"iteration":549,"passed_time":6.08628677,"remaining_time":4.979689175},
{"learn":[0.1846795203],"iteration":550,"passed_time":6.096137524,"remaining_time":4.967632937},
{"learn":[0.1845742316],"iteration":551,"passed_time":6.106345624,"remaining_time":4.955874709},
{"learn":[0.1845133655],"iteration":552,"passed_time":6.116923995,"remaining_time":4.944421385},
{"learn":[0.1844197499],"iteration":553,"passed_time":6.127289809,"remaining_time":4.932800099},
{"learn":[0.1843263083],"iteration":554,"passed_time":6.138106171,"remaining_time":4.921544587},
{"learn":[0.1843118538],"iteration":555,"passed_time":6.148724439,"remaining_time":4.910132466},
{"learn":[0.1842376015],"iteration":556,"passed_time":6.159067819,"remaining_time":4.898504567},
{"learn":[0.184121289],"iteration":557,"passed_time":6.170027239,"remaining_time":4.887369247},
{"learn":[0.1840530091],"iteration":558,"passed_time":6.181037935,"remaining_time":4.876275008},
{"learn":[0.1839137887],"iteration":559,"passed_time":6.191291339,"remaining_time":4.864586052},
{"learn":[0.1838758082],"iteration":560,"passed_time":6.202322524,"remaining_time":4.853510852},
{"learn":[0.1837113598],"iteration":561,"passed_time":6.213743975,"remaining_time":4.842739966},
{"learn":[0.1836176055],"iteration":562,"passed_time":6.22424098,"remaining_time":4.831249215},
{"learn":[0.1835721153],"iteration":563,"passed_time":6.235228637,"remaining_time":4.820141287},
{"learn":[0.1835677369],"iteration":564,"passed_time":6.245102988,"remaining_time":4.808176637},
{"learn":[0.1834012328],"iteration":565,"passed_time":6.256785988,"remaining_time":4.797606217},
{"learn":[0.1833138507],"iteration":566,"passed_time":6.267866262,"remaining_time":4.78657159},
{"learn":[0.1831565289],"iteration":567,"passed_time":6.27917522,"remaining_time":4.775710731},
{"learn":[0.1830760076],"iteration":568,"passed_time":6.289579097,"remaining_time":4.764162726},
{"learn":[0.1829477563],"iteration":569,"passed_time":6.300953436,"remaining_time":4.753350837},
{"learn":[0.1828972962],"iteration":570,"passed_time":6.311828547,"remaining_time":4.742161903},
{"learn":[0.1827922622],"iteration":571,"passed_time":6.322259723,"remaining_time":4.730641891},
{"learn":[0.1827593817],"iteration":572,"passed_time":6.333234475,"remaining_time":4.719530752},
{"learn":[0.1826565887],"iteration":573,"passed_time":6.343851607,"remaining_time":4.708154677},
{"learn":[0.1825981057],"iteration":574,"passed_time":6.354184258,"remaining_time":4.696570973},
{"learn":[0.1825934881],"iteration":575,"passed_time":6.364351185,"remaining_time":4.684869623},
{"learn":[0.1825398812],"iteration":576,"passed_time":6.374698175,"remaining_time":4.673305595},
{"learn":[0.1823952348],"iteration":577,"passed_time":6.385575713,"remaining_time":4.662133133},
{"learn":[0.1823173142],"iteration":578,"passed_time":6.396590678,"remaining_time":4.651061616},
{"learn":[0.1822749826],"iteration":579,"passed_time":6.40656927,"remaining_time":4.639239816},
{"learn":[0.1822140295],"iteration":580,"passed_time":6.417247029,"remaining_time":4.62792858},
{"learn":[0.1820858604],"iteration":581,"passed_time":6.428284536,"remaining_time":4.616877897},
{"learn":[0.1819903468],"iteration":582,"passed_time":6.43859594,"remaining_time":4.605307902},
{"learn":[0.1819156007],"iteration":583,"passed_time":6.450329057,"remaining_time":4.594754945},
{"learn":[0.1818050129],"iteration":584,"passed_time":6.461033096,"remaining_time":4.583467923},
{"learn":[0.1816689018],"iteration":585,"passed_time":6.471636101,"remaining_time":4.572111511},
{"learn":[0.1815482421],"iteration":586,"passed_time":6.482545269,"remaining_time":4.560973077},
{"learn":[0.1814661666],"iteration":587,"passed_time":6.493392087,"remaining_time":4.549791734},
{"learn":[0.1813922455],"iteration":588,"passed_time":6.504059915,"remaining_time":4.53848663},
{"learn":[0.1813875344],"iteration":589,"passed_time":6.514308427,"remaining_time":4.526892297},
{"learn":[0.1813471704],"iteration":590,"passed_time":6.524545007,"remaining_time":4.515294261},
{"learn":[0.1812468225],"iteration":591,"passed_time":6.535721909,"remaining_time":4.504348883},
{"learn":[0.1812421211],"iteration":592,"passed_time":6.546599096,"remaining_time":4.493197018},
{"learn":[0.1811821662],"iteration":593,"passed_time":6.557382953,"remaining_time":4.481982288},
{"learn":[0.1810936947],"iteration":594,"passed_time":6.567835944,"remaining_time":4.470543794},
{"learn":[0.1810454345],"iteration":595,"passed_time":6.579244054,"remaining_time":4.459756036},
{"learn":[0.1810409302],"iteration":596,"passed_time":6.589491422,"remaining_time":4.448182651},
{"learn":[0.1810157199],"iteration":597,"passed_time":6.599705812,"remaining_time":4.436591532},
{"learn":[0.1808944672],"iteration":598,"passed_time":6.611012866,"remaining_time":4.425736493},
{"learn":[0.1808494849],"iteration":599,"passed_time":6.621011982,"remaining_time":4.414007988},
{"learn":[0.1808037467],"iteration":600,"passed_time":6.631524082,"remaining_time":4.402625805},
{"learn":[0.1807454844],"iteration":601,"passed_time":6.64309258,"remaining_time":4.391944928},
{"learn":[0.1806814561],"iteration":602,"passed_time":6.65379855,"remaining_time":4.380693241},
{"learn":[0.1805806279],"iteration":603,"passed_time":6.664164638,"remaining_time":4.369220524},
{"learn":[0.1805293877],"iteration":604,"passed_time":6.674996941,"remaining_time":4.358055854},
{"learn":[0.1804444032],"iteration":605,"passed_time":6.685551817,"remaining_time":4.346711908},
{"learn":[0.1803863002],"iteration":606,"passed_time":6.695907884,"remaining_time":4.335241843},
{"learn":[0.1802784763],"iteration":607,"passed_time":6.707294037,"remaining_time":4.324439577},
{"learn":[0.1802371294],"iteration":608,"passed_time":6.717635087,"remaining_time":4.312964399},
{"learn":[0.1801903438],"iteration":609,"passed_time":6.728051098,"remaining_time":4.301540866},
{"learn":[0.180138461],"iteration":610,"passed_time":6.738791446,"remaining_time":4.290327124},
{"learn":[0.1800581478],"iteration":611,"passed_time":6.749037525,"remaining_time":4.278801568},
{"learn":[0.1800507028],"iteration":612,"passed_time":6.759329431,"remaining_time":4.267309119},
{"learn":[0.1800027276],"iteration":613,"passed_time":6.769930493,"remaining_time":4.256014935},
{"learn":[0.1799206929],"iteration":614,"passed_time":6.780703905,"remaining_time":4.2448309},
{"learn":[0.1797753522],"iteration":615,"passed_time":6.792344881,"remaining_time":4.234189017},
{"learn":[0.1796679102],"iteration":616,"passed_time":6.803526255,"remaining_time":4.223258599},
{"learn":[0.1795553184],"iteration":617,"passed_time":6.813650627,"remaining_time":4.211674012},
{"learn":[0.1795051951],"iteration":618,"passed_time":6.824177519,"remaining_time":4.200341898},
{"learn":[0.1794059101],"iteration":619,"passed_time":6.834896838,"remaining_time":4.18913032},
{"learn":[0.1793259359],"iteration":620,"passed_time":6.845392024,"remaining_time":4.177783538},
{"learn":[0.179272767],"iteration":621,"passed_time":6.85705477,"remaining_time":4.16714904},
{"learn":[0.1791673989],"iteration":622,"passed_time":6.867870774,"remaining_time":4.155998847},
{"learn":[0.1790755344],"iteration":623,"passed_time":6.878900935,"remaining_time":4.144978769},
{"learn":[0.178973031],"iteration":624,"passed_time":6.890281377,"remaining_time":4.134168826},
{"learn":[0.1789200806],"iteration":625,"passed_time":6.901348278,"remaining_time":4.123169738},
{"learn":[0.1788680796],"iteration":626,"passed_time":6.911400579,"remaining_time":4.111566852},
{"learn":[0.1787843682],"iteration":627,"passed_time":6.92300763,"remaining_time":4.10088987},
{"learn":[0.1786830419],"iteration":628,"passed_time":6.934661117,"remaining_time":4.09023732},
{"learn":[0.1785970334],"iteration":629,"passed_time":6.946259015,"remaining_time":4.079548945},
{"learn":[0.1785368251],"iteration":630,"passed_time":6.95752687,"remaining_time":4.068664683},
{"learn":[0.1784007035],"iteration":631,"passed_time":6.968954183,"remaining_time":4.057872056},
{"learn":[0.1783572182],"iteration":632,"passed_time":6.979716046,"remaining_time":4.04669161},
{"learn":[0.1782472075],"iteration":633,"passed_time":6.990300801,"remaining_time":4.035410241},
{"learn":[0.1781615964],"iteration":634,"passed_time":7.001384221,"remaining_time":4.024417702},
{"learn":[0.1780785885],"iteration":635,"passed_time":7.011495061,"remaining_time":4.012868243},
{"learn":[0.1779835695],"iteration":636,"passed_time":7.02313187,"remaining_time":4.002192887},
{"learn":[0.1778260465],"iteration":637,"passed_time":7.035136003,"remaining_time":3.991722936},
{"learn":[0.1778219157],"iteration":638,"passed_time":7.044932854,"remaining_time":3.98000119},
{"learn":[0.177742469],"iteration":639,"passed_time":7.055490804,"remaining_time":3.968713577},
{"learn":[0.1776374288],"iteration":640,"passed_time":7.06655796,"remaining_time":3.957713428},
{"learn":[0.1775879183],"iteration":641,"passed_time":7.076585985,"remaining_time":3.946133618},
{"learn":[0.177517751],"iteration":642,"passed_time":7.087157443,"remaining_time":3.934860353},
{"learn":[0.1774487073],"iteration":643,"passed_time":7.097792346,"remaining_time":3.92362434},
{"learn":[0.1774283089],"iteration":644,"passed_time":7.107871721,"remaining_time":3.912084435},
{"learn":[0.1773186202],"iteration":645,"passed_time":7.118935874,"remaining_time":3.901088699},
{"learn":[0.1773040995],"iteration":646,"passed_time":7.129505945,"remaining_time":3.889823182},
{"learn":[0.1771728282],"iteration":647,"passed_time":7.140188305,"remaining_time":3.878620808},
{"learn":[0.177153205],"iteration":648,"passed_time":7.151222127,"remaining_time":3.867610118},
{"learn":[0.1770315977],"iteration":649,"passed_time":7.1616744,"remaining_time":3.856286215},
{"learn":[0.1769540779],"iteration":650,"passed_time":7.172459782,"remaining_time":3.84514357},
{"learn":[0.176832372],"iteration":651,"passed_time":7.184526621,"remaining_time":3.834685988},
{"learn":[0.1767273624],"iteration":652,"passed_time":7.195107278,"remaining_time":3.82343373},
{"learn":[0.1766608506],"iteration":653,"passed_time":7.20542679,"remaining_time":3.812045366},
{"learn":[0.1765823872],"iteration":654,"passed_time":7.216187524,"remaining_time":3.800892666},
{"learn":[0.176538543],"iteration":655,"passed_time":7.226498645,"remaining_time":3.789505387},
{"learn":[0.1764158336],"iteration":656,"passed_time":7.237640913,"remaining_time":3.778555302},
{"learn":[0.1763786613],"iteration":657,"passed_time":7.248195328,"remaining_time":3.767299092},
{"learn":[0.1763746298],"iteration":658,"passed_time":7.25804159,"remaining_time":3.755678577},
{"learn":[0.1762724702],"iteration":659,"passed_time":7.269045104,"remaining_time":3.744659599},
{"learn":[0.1762181637],"iteration":660,"passed_time":7.279681016,"remaining_time":3.73345214},
{"learn":[0.1761164291],"iteration":661,"passed_time":7.289729927,"remaining_time":3.7219467},
{"learn":[0.176112852],"iteration":662,"passed_time":7.300084735,"remaining_time":3.71060114},
{"learn":[0.1760433339],"iteration":663,"passed_time":7.311229451,"remaining_time":3.699658276},
{"learn":[0.1759096567],"iteration":664,"passed_time":7.322157008,"remaining_time":3.68860541},
{"learn":[0.1758730482],"iteration":665,"passed_time":7.332928912,"remaining_time":3.67747486},
{"learn":[0.1758687286],"iteration":666,"passed_time":7.343238529,"remaining_time":3.666114588},
{"learn":[0.1758019075],"iteration":667,"passed_time":7.353813728,"remaining_time":3.654889458},
{"learn":[0.1757411356],"iteration":668,"passed_time":7.364637232,"remaining_time":3.643789124},
{"learn":[0.1756900145],"iteration":669,"passed_time":7.374801098,"remaining_time":3.63236472},
{"learn":[0.1756350516],"iteration":670,"passed_time":7.385287307,"remaining_time":3.621102122},
{"learn":[0.1755642224],"iteration":671,"passed_time":7.396522487,"remaining_time":3.610207404},
{"learn":[0.1754488003],"iteration":672,"passed_time":7.406881066,"remaining_time":3.598885748},
{"learn":[0.1753409586],"iteration":673,"passed_time":7.417592939,"remaining_time":3.587737831},
{"learn":[0.1752476326],"iteration":674,"passed_time":7.430421013,"remaining_time":3.577610117},
{"learn":[0.1751808471],"iteration":675,"passed_time":7.440635636,"remaining_time":3.566221814},
{"learn":[0.1750510615],"iteration":676,"passed_time":7.451596842,"remaining_time":3.555193176},
{"learn":[0.1749872713],"iteration":677,"passed_time":7.462428106,"remaining_time":3.544103024},
{"learn":[0.1748991758],"iteration":678,"passed_time":7.473367607,"remaining_time":3.533064804},
{"learn":[0.1747797526],"iteration":679,"passed_time":7.483852864,"remaining_time":3.521813113},
{"learn":[0.1746871352],"iteration":680,"passed_time":7.515090653,"remaining_time":3.520284755},
{"learn":[0.1745956915],"iteration":681,"passed_time":7.529688346,"remaining_time":3.510910402},
{"learn":[0.1745323255],"iteration":682,"passed_time":7.542010484,"remaining_time":3.500464603},
{"learn":[0.1744522467],"iteration":683,"passed_time":7.552351059,"remaining_time":3.489097858},
{"learn":[0.1743398881],"iteration":684,"passed_time":7.563547601,"remaining_time":3.478127729},
{"learn":[0.1742410445],"iteration":685,"passed_time":7.574553958,"remaining_time":3.467069887},
{"learn":[0.1741541009],"iteration":686,"passed_time":7.58569396,"remaining_time":3.456073085},
{"learn":[0.1740508779],"iteration":687,"passed_time":7.596660998,"remaining_time":3.444997429},
{"learn":[0.1739492213],"iteration":688,"passed_time":7.607241524,"remaining_time":3.433747626},
{"learn":[0.173944137],"iteration":689,"passed_time":7.617178373,"remaining_time":3.422210574},
{"learn":[0.1738503819],"iteration":690,"passed_time":7.628074154,"remaining_time":3.411106966},
{"learn":[0.1737535368],"iteration":691,"passed_time":7.639016681,"remaining_time":3.400024765},
{"learn":[0.1736656243],"iteration":692,"passed_time":7.649182043,"remaining_time":3.388598683},
{"learn":[0.1736132912],"iteration":693,"passed_time":7.660119792,"remaining_time":3.377516796},
{"learn":[0.1735113455],"iteration":694,"passed_time":7.671194454,"remaining_time":3.366495408},
{"learn":[0.1734608736],"iteration":695,"passed_time":7.6813474,"remaining_time":3.355071278},
{"learn":[0.1733892484],"iteration":696,"passed_time":7.69267447,"remaining_time":3.344161212},
{"learn":[0.1733857037],"iteration":697,"passed_time":7.702665181,"remaining_time":3.332671754},
{"learn":[0.173382637],"iteration":698,"passed_time":7.712715472,"remaining_time":3.321212242},
{"learn":[0.1733795545],"iteration":699,"passed_time":7.723235812,"remaining_time":3.309958205},
{"learn":[0.1733429856],"iteration":700,"passed_time":7.733422869,"remaining_time":3.298564105},
{"learn":[0.1733399358],"iteration":701,"passed_time":7.743194713,"remaining_time":3.286997186},
{"learn":[0.1733377204],"iteration":702,"passed_time":7.753437995,"remaining_time":3.275634544},
{"learn":[0.1732615165],"iteration":703,"passed_time":7.763656907,"remaining_time":3.264264836},
{"learn":[0.1731593763],"iteration":704,"passed_time":7.774572179,"remaining_time":3.253189777},
{"learn":[0.1731130678],"iteration":705,"passed_time":7.784608235,"remaining_time":3.241749038},
{"learn":[0.173047803],"iteration":706,"passed_time":7.795034293,"remaining_time":3.230473901},
{"learn":[0.1729500655],"iteration":707,"passed_time":7.80597882,"remaining_time":3.219414994},
{"learn":[0.1728128253],"iteration":708,"passed_time":7.817184675,"remaining_time":3.208463668},
{"learn":[0.1727464986],"iteration":709,"passed_time":7.827783209,"remaining_time":3.197263564},
{"learn":[0.1727091897],"iteration":710,"passed_time":7.838706275,"remaining_time":3.186197065},
{"learn":[0.1726312105],"iteration":711,"passed_time":7.849503163,"remaining_time":3.175079931},
{"learn":[0.1726012747],"iteration":712,"passed_time":7.859996287,"remaining_time":3.163841423},
{"learn":[0.1725341917],"iteration":713,"passed_time":7.870502765,"remaining_time":3.152610351},
{"learn":[0.172459461],"iteration":714,"passed_time":7.88092571,"remaining_time":3.14134801},
{"learn":[0.1724507404],"iteration":715,"passed_time":7.891323251,"remaining_time":3.130077938},
{"learn":[0.1724024058],"iteration":716,"passed_time":7.902447101,"remaining_time":3.119096973},
{"learn":[0.1722950722],"iteration":717,"passed_time":7.912839926,"remaining_time":3.107828495},
{"learn":[0.172292109],"iteration":718,"passed_time":7.923087504,"remaining_time":3.096505686},
{"learn":[0.1721876538],"iteration":719,"passed_time":7.934105666,"remaining_time":3.085485537},
{"learn":[0.1720853327],"iteration":720,"passed_time":7.944699627,"remaining_time":3.074301243},
{"learn":[0.1720172131],"iteration":721,"passed_time":7.955801293,"remaining_time":3.063314071},
{"learn":[0.1719384606],"iteration":722,"passed_time":7.966890142,"remaining_time":3.052321673},
{"learn":[0.1718290703],"iteration":723,"passed_time":7.977353867,"remaining_time":3.041090701},
{"learn":[0.1717813155],"iteration":724,"passed_time":7.98862305,"remaining_time":3.030167364},
{"learn":[0.171733138],"iteration":725,"passed_time":7.999595894,"remaining_time":3.019131233},
{"learn":[0.171659122],"iteration":726,"passed_time":8.010210401,"remaining_time":3.007960714},
{"learn":[0.1716413666],"iteration":727,"passed_time":8.020959963,"remaining_time":2.996842184},
{"learn":[0.1715684897],"iteration":728,"passed_time":8.031711298,"remaining_time":2.985725325},
{"learn":[0.1714819142],"iteration":729,"passed_time":8.042453388,"remaining_time":2.974606048},
{"learn":[0.1714772932],"iteration":730,"passed_time":8.052865636,"remaining_time":2.963366424},
{"learn":[0.1714221872],"iteration":731,"passed_time":8.063567623,"remaining_time":2.952235141},
{"learn":[0.1714197543],"iteration":732,"passed_time":8.073427498,"remaining_time":2.940798284},
{"learn":[0.1713712629],"iteration":733,"passed_time":8.084403574,"remaining_time":2.929770233},
{"learn":[0.1713665332],"iteration":734,"passed_time":8.094245683,"remaining_time":2.918333478},
{"learn":[0.1713639246],"iteration":735,"passed_time":8.104270318,"remaining_time":2.906966527},
{"learn":[0.1712554209],"iteration":736,"passed_time":8.115284465,"remaining_time":2.895956329},
{"learn":[0.1712121506],"iteration":737,"passed_time":8.125289498,"remaining_time":2.884587871},
{"learn":[0.1711678707],"iteration":738,"passed_time":8.136438849,"remaining_time":2.873627252},
{"learn":[0.1710838755],"iteration":739,"passed_time":8.147397817,"remaining_time":2.862599233},
{"learn":[0.1710093317],"iteration":740,"passed_time":8.157682316,"remaining_time":2.851335654},
{"learn":[0.1710053643],"iteration":741,"passed_time":8.168081525,"remaining_time":2.8401146},
{"learn":[0.1709337163],"iteration":742,"passed_time":8.179278516,"remaining_time":2.829171707},
{"learn":[0.170876352],"iteration":743,"passed_time":8.189867026,"remaining_time":2.818018762},
{"learn":[0.170825531],"iteration":744,"passed_time":8.200608425,"remaining_time":2.806919662},
{"learn":[0.1707045655],"iteration":745,"passed_time":8.212815942,"remaining_time":2.79632071},
{"learn":[0.1706637593],"iteration":746,"passed_time":8.223360806,"remaining_time":2.785154329},
{"learn":[0.1706124536],"iteration":747,"passed_time":8.234302933,"remaining_time":2.774123448},
{"learn":[0.170546624],"iteration":748,"passed_time":8.245483808,"remaining_time":2.763172812},
{"learn":[0.1704718147],"iteration":749,"passed_time":8.255829059,"remaining_time":2.75194302},
{"learn":[0.170412972],"iteration":750,"passed_time":8.266422088,"remaining_time":2.740797736},
{"learn":[0.1703151657],"iteration":751,"passed_time":8.277302591,"remaining_time":2.729748727},
{"learn":[0.1702259193],"iteration":752,"passed_time":8.287773089,"remaining_time":2.718565674},
{"learn":[0.1701708947],"iteration":753,"passed_time":8.298547794,"remaining_time":2.707483763},
{"learn":[0.1701241208],"iteration":754,"passed_time":8.30922888,"remaining_time":2.696372286},
{"learn":[0.1700778274],"iteration":755,"passed_time":8.319378815,"remaining_time":2.685090517},
{"learn":[0.1700406203],"iteration":756,"passed_time":8.330413673,"remaining_time":2.674095802},
{"learn":[0.1700379287],"iteration":757,"passed_time":8.340266967,"remaining_time":2.662723755},
{"learn":[0.1700343973],"iteration":758,"passed_time":8.351063727,"remaining_time":2.651655281},
{"learn":[0.1699599476],"iteration":759,"passed_time":8.361819501,"remaining_time":2.640574579},
{"learn":[0.1698888003],"iteration":760,"passed_time":8.37207015,"remaining_time":2.629336092},
{"learn":[0.1698025659],"iteration":761,"passed_time":8.382743616,"remaining_time":2.618232258},
{"learn":[0.1697571386],"iteration":762,"passed_time":8.393645988,"remaining_time":2.607200654},
{"learn":[0.1697165644],"iteration":763,"passed_time":8.403524742,"remaining_time":2.595853193},
{"learn":[0.169674788],"iteration":764,"passed_time":8.41487112,"remaining_time":2.584960409},
{"learn":[0.1695493621],"iteration":765,"passed_time":8.426308474,"remaining_time":2.574094233},
{"learn":[0.1695240712],"iteration":766,"passed_time":8.436244346,"remaining_time":2.562770447},
{"learn":[0.1694374791],"iteration":767,"passed_time":8.44741831,"remaining_time":2.551824281},
{"learn":[0.169364544],"iteration":768,"passed_time":8.458456649,"remaining_time":2.540836783},
{"learn":[0.1692469896],"iteration":769,"passed_time":8.469080061,"remaining_time":2.529725213},
{"learn":[0.1691946733],"iteration":770,"passed_time":8.479901976,"remaining_time":2.518673868},
{"learn":[0.1691923215],"iteration":771,"passed_time":8.490451079,"remaining_time":2.507542547},
{"learn":[0.1691172222],"iteration":772,"passed_time":8.500847891,"remaining_time":2.496368009},
{"learn":[0.169028916],"iteration":773,"passed_time":8.511969413,"remaining_time":2.48540709},
{"learn":[0.1689720185],"iteration":774,"passed_time":8.523459941,"remaining_time":2.474552886},
{"learn":[0.1688617564],"iteration":775,"passed_time":8.533878299,"remaining_time":2.46338755},
{"learn":[0.1688282369],"iteration":776,"passed_time":8.54467102,"remaining_time":2.45233158},
{"learn":[0.1687537747],"iteration":777,"passed_time":8.555814203,"remaining_time":2.441376289},
{"learn":[0.1686799188],"iteration":778,"passed_time":8.565959215,"remaining_time":2.430137338},
{"learn":[0.1686399772],"iteration":779,"passed_time":8.576759592,"remaining_time":2.419086039},
{"learn":[0.1685999864],"iteration":780,"passed_time":8.587089786,"remaining_time":2.407903538},
{"learn":[0.1685516031],"iteration":781,"passed_time":8.597793235,"remaining_time":2.39682727},
{"learn":[0.1684946506],"iteration":782,"passed_time":8.609610178,"remaining_time":2.386060547},
{"learn":[0.1683903512],"iteration":783,"passed_time":8.620972114,"remaining_time":2.375165787},
{"learn":[0.1682949006],"iteration":784,"passed_time":8.631687758,"remaining_time":2.364092825},
{"learn":[0.1682291442],"iteration":785,"passed_time":8.642534108,"remaining_time":2.35305636},
{"learn":[0.1681387281],"iteration":786,"passed_time":8.653535246,"remaining_time":2.342062271},
{"learn":[0.1680426695],"iteration":787,"passed_time":8.664244363,"remaining_time":2.3309896},
{"learn":[0.1679402919],"iteration":788,"passed_time":8.675444498,"remaining_time":2.320049162},
{"learn":[0.1678641806],"iteration":789,"passed_time":8.686480189,"remaining_time":2.309064354},
{"learn":[0.1678156551],"iteration":790,"passed_time":8.696656892,"remaining_time":2.297852453},
{"learn":[0.1677062253],"iteration":791,"passed_time":8.708416641,"remaining_time":2.287058916},
{"learn":[0.1676036626],"iteration":792,"passed_time":8.719733412,"remaining_time":2.276147309},
{"learn":[0.1675753755],"iteration":793,"passed_time":8.729958984,"remaining_time":2.264951575},
{"learn":[0.1675590978],"iteration":794,"passed_time":8.738276472,"remaining_time":2.25326626},
{"learn":[0.1674949998],"iteration":795,"passed_time":8.748511562,"remaining_time":2.242080853},
{"learn":[0.1674487624],"iteration":796,"passed_time":8.759524262,"remaining_time":2.231095891},
{"learn":[0.1672782343],"iteration":797,"passed_time":8.770682364,"remaining_time":2.220147666},
{"learn":[0.1672140006],"iteration":798,"passed_time":8.780990978,"remaining_time":2.208985215},
{"learn":[0.1671339305],"iteration":799,"passed_time":8.792238611,"remaining_time":2.198059653},
{"learn":[0.1670549515],"iteration":800,"passed_time":8.803283554,"remaining_time":2.18708293},
{"learn":[0.1670526191],"iteration":801,"passed_time":8.813271958,"remaining_time":2.175845197},
{"learn":[0.1669828391],"iteration":802,"passed_time":8.824109864,"remaining_time":2.164818983},
{"learn":[0.1669094986],"iteration":803,"passed_time":8.835151417,"remaining_time":2.153842883},
{"learn":[0.1668473658],"iteration":804,"passed_time":8.845432199,"remaining_time":2.142682334},
{"learn":[0.1668196875],"iteration":805,"passed_time":8.855867935,"remaining_time":2.131561265},
{"learn":[0.1667384805],"iteration":806,"passed_time":8.86746096,"remaining_time":2.120718668},
{"learn":[0.1666971374],"iteration":807,"passed_time":8.877599824,"remaining_time":2.109528671},
{"learn":[0.1666660884],"iteration":808,"passed_time":8.889463501,"remaining_time":2.09874849},
{"learn":[0.166663321],"iteration":809,"passed_time":8.900836431,"remaining_time":2.087850521},
{"learn":[0.1665486424],"iteration":810,"passed_time":8.912047489,"remaining_time":2.076913657},
{"learn":[0.1664632969],"iteration":811,"passed_time":8.92352281,"remaining_time":2.066037301},
{"learn":[0.1663878221],"iteration":812,"passed_time":8.934875629,"remaining_time":2.055131295},
{"learn":[0.1662946877],"iteration":813,"passed_time":8.945833184,"remaining_time":2.044133873},
{"learn":[0.1662554274],"iteration":814,"passed_time":8.956529315,"remaining_time":2.033077207},
{"learn":[0.166198964],"iteration":815,"passed_time":8.967175077,"remaining_time":2.022010066},
{"learn":[0.1661887047],"iteration":816,"passed_time":8.977086125,"remaining_time":2.010779389},
{"learn":[0.1661252752],"iteration":817,"passed_time":8.987955806,"remaining_time":1.999765228},
{"learn":[0.1660408419],"iteration":818,"passed_time":9.000195282,"remaining_time":1.989054147},
{"learn":[0.1660286535],"iteration":819,"passed_time":9.010753323,"remaining_time":1.977970242},
{"learn":[0.1659771037],"iteration":820,"passed_time":9.021572761,"remaining_time":1.966944609},
{"learn":[0.1658793227],"iteration":821,"passed_time":9.032371038,"remaining_time":1.955914896},
{"learn":[0.1658076509],"iteration":822,"passed_time":9.042761715,"remaining_time":1.944798084},
{"learn":[0.1657955694],"iteration":823,"passed_time":9.053596507,"remaining_time":1.933777895},
{"learn":[0.1657106862],"iteration":824,"passed_time":9.06467324,"remaining_time":1.922809475},
{"learn":[0.1656238042],"iteration":825,"passed_time":9.075105118,"remaining_time":1.911704952},
{"learn":[0.1655660896],"iteration":826,"passed_time":9.085732679,"remaining_time":1.900642991},
{"learn":[0.1655485174],"iteration":827,"passed_time":9.096196352,"remaining_time":1.889548035},
{"learn":[0.1655068574],"iteration":828,"passed_time":9.106584202,"remaining_time":1.878438961},
{"learn":[0.1654341115],"iteration":829,"passed_time":9.117384926,"remaining_time":1.86741619},
{"learn":[0.1653645097],"iteration":830,"passed_time":9.127666998,"remaining_time":1.856288475},
{"learn":[0.1652586962],"iteration":831,"passed_time":9.138314315,"remaining_time":1.845236544},
{"learn":[0.1652345809],"iteration":832,"passed_time":9.149598591,"remaining_time":1.834313283},
{"learn":[0.1652095554],"iteration":833,"passed_time":9.159591093,"remaining_time":1.82313204},
{"learn":[0.1651467287],"iteration":834,"passed_time":9.170623903,"remaining_time":1.812159214},
{"learn":[0.165141273],"iteration":835,"passed_time":9.181146639,"remaining_time":1.801086183},
{"learn":[0.1650769279],"iteration":836,"passed_time":9.191527593,"remaining_time":1.789986855},
{"learn":[0.1649837927],"iteration":837,"passed_time":9.202589741,"remaining_time":1.779020928},
{"learn":[0.1649634466],"iteration":838,"passed_time":9.21372703,"remaining_time":1.768069192},
{"learn":[0.1649357938],"iteration":839,"passed_time":9.22390341,"remaining_time":1.756933983},
{"learn":[0.1648662098],"iteration":840,"passed_time":9.234857938,"remaining_time":1.745948171},
{"learn":[0.1648251036],"iteration":841,"passed_time":9.245412532,"remaining_time":1.734887387},
{"learn":[0.1647500333],"iteration":842,"passed_time":9.25566309,"remaining_time":1.723771181},
{"learn":[0.1646902929],"iteration":843,"passed_time":9.267028538,"remaining_time":1.712863095},
{"learn":[0.1646347578],"iteration":844,"passed_time":9.278112532,"remaining_time":1.701902299},
{"learn":[0.1645925447],"iteration":845,"passed_time":9.288260926,"remaining_time":1.690770901},
{"learn":[0.1645425834],"iteration":846,"passed_time":9.29882365,"remaining_time":1.679716669},
{"learn":[0.164512362],"iteration":847,"passed_time":9.309847938,"remaining_time":1.668746329},
{"learn":[0.1643768253],"iteration":848,"passed_time":9.320496368,"remaining_time":1.657709012},
{"learn":[0.16430099],"iteration":849,"passed_time":9.331462634,"remaining_time":1.6467287},
{"learn":[0.1641731612],"iteration":850,"passed_time":9.342454726,"remaining_time":1.635752943},
{"learn":[0.1641475571],"iteration":851,"passed_time":9.352804831,"remaining_time":1.624665628},
{"learn":[0.1640505396],"iteration":852,"passed_time":9.363554209,"remaining_time":1.61364885},
{"learn":[0.1639198601],"iteration":853,"passed_time":9.374429315,"remaining_time":1.602654192},
{"learn":[0.1638728242],"iteration":854,"passed_time":9.38538033,"remaining_time":1.591672687},
{"learn":[0.1638547251],"iteration":855,"passed_time":9.396591402,"remaining_time":1.580735002},
{"learn":[0.1637939214],"iteration":856,"passed_time":9.408304674,"remaining_time":1.569880477},
{"learn":[0.1637086781],"iteration":857,"passed_time":9.419242161,"remaining_time":1.558895556},
{"learn":[0.163628963],"iteration":858,"passed_time":9.430743205,"remaining_time":1.54800325},
{"learn":[0.1635764757],"iteration":859,"passed_time":9.441550148,"remaining_time":1.536996536},
{"learn":[0.1635079487],"iteration":860,"passed_time":9.452110431,"remaining_time":1.525950464},
{"learn":[0.1634320657],"iteration":861,"passed_time":9.463112579,"remaining_time":1.51497626},
{"learn":[0.1633873766],"iteration":862,"passed_time":9.474010372,"remaining_time":1.503985424},
{"learn":[0.1633404648],"iteration":863,"passed_time":9.484251547,"remaining_time":1.492891447},
{"learn":[0.163279114],"iteration":864,"passed_time":9.495251853,"remaining_time":1.481917919},
{"learn":[0.1632251344],"iteration":865,"passed_time":9.506017167,"remaining_time":1.470907968},
{"learn":[0.163130579],"iteration":866,"passed_time":9.516291522,"remaining_time":1.459823267},
{"learn":[0.1630649755],"iteration":867,"passed_time":9.527548782,"remaining_time":1.448889907},
{"learn":[0.1629899106],"iteration":868,"passed_time":9.53906354,"remaining_time":1.437994619},
{"learn":[0.1629320786],"iteration":869,"passed_time":9.549286711,"remaining_time":1.426904911},
{"learn":[0.162909274],"iteration":870,"passed_time":9.559982492,"remaining_time":1.415887189},
{"learn":[0.1628310778],"iteration":871,"passed_time":9.570782671,"remaining_time":1.40488553},
{"learn":[0.1627246302],"iteration":872,"passed_time":9.581345612,"remaining_time":1.39384982},
{"learn":[0.1626581387],"iteration":873,"passed_time":9.59252962,"remaining_time":1.382904728},
{"learn":[0.1626188432],"iteration":874,"passed_time":9.603049289,"remaining_time":1.371864184},
{"learn":[0.1625440413],"iteration":875,"passed_time":9.613380912,"remaining_time":1.360798211},
{"learn":[0.1625391123],"iteration":876,"passed_time":9.62410399,"remaining_time":1.349788815},
{"learn":[0.1624785439],"iteration":877,"passed_time":9.634339195,"remaining_time":1.33871228},
{"learn":[0.1624412964],"iteration":878,"passed_time":9.645028379,"remaining_time":1.327700152},
{"learn":[0.1623834777],"iteration":879,"passed_time":9.656480914,"remaining_time":1.316792852},
{"learn":[0.1623272639],"iteration":880,"passed_time":9.666849052,"remaining_time":1.30573784},
{"learn":[0.1622969985],"iteration":881,"passed_time":9.677198865,"remaining_time":1.294681934},
{"learn":[0.1622433006],"iteration":882,"passed_time":9.68788176,"remaining_time":1.283671762},
{"learn":[0.1621562382],"iteration":883,"passed_time":9.698283962,"remaining_time":1.272625497},
{"learn":[0.1621154819],"iteration":884,"passed_time":9.709212676,"remaining_time":1.261649105},
{"learn":[0.1620784399],"iteration":885,"passed_time":9.719997749,"remaining_time":1.250654338},
{"learn":[0.1620189516],"iteration":886,"passed_time":9.730479738,"remaining_time":1.239621432},
{"learn":[0.1619593708],"iteration":887,"passed_time":9.741106373,"remaining_time":1.228608011},
{"learn":[0.1618943698],"iteration":888,"passed_time":9.752017059,"remaining_time":1.217630926},
{"learn":[0.1618346214],"iteration":889,"passed_time":9.762646733,"remaining_time":1.206619259},
{"learn":[0.1617940045],"iteration":890,"passed_time":9.77347819,"remaining_time":1.195633134},
{"learn":[0.1617501342],"iteration":891,"passed_time":9.785073358,"remaining_time":1.184739824},
{"learn":[0.1617097558],"iteration":892,"passed_time":9.795164142,"remaining_time":1.173664684},
{"learn":[0.1616496468],"iteration":893,"passed_time":9.806440663,"remaining_time":1.162732338},
{"learn":[0.1616468531],"iteration":894,"passed_time":9.816437246,"remaining_time":1.151649062},
{"learn":[0.1615674661],"iteration":895,"passed_time":9.827148412,"remaining_time":1.140651155},
{"learn":[0.1614713994],"iteration":896,"passed_time":9.838048095,"remaining_time":1.129675534},
{"learn":[0.1613976342],"iteration":897,"passed_time":9.849069777,"remaining_time":1.118713939},
{"learn":[0.1613213237],"iteration":898,"passed_time":9.859721797,"remaining_time":1.10771068},
{"learn":[0.161301462],"iteration":899,"passed_time":9.870868628,"remaining_time":1.096763181},
{"learn":[0.1612526882],"iteration":900,"passed_time":9.881039922,"remaining_time":1.085708049},
{"learn":[0.1611917617],"iteration":901,"passed_time":9.891811728,"remaining_time":1.074720121},
{"learn":[0.161152918],"iteration":902,"passed_time":9.902654307,"remaining_time":1.063740274},
{"learn":[0.161098639],"iteration":903,"passed_time":9.913015605,"remaining_time":1.052709622},
{"learn":[0.1609703436],"iteration":904,"passed_time":9.924357386,"remaining_time":1.041783372},
{"learn":[0.1609212828],"iteration":905,"passed_time":9.935240091,"remaining_time":1.030808575},
{"learn":[0.1608669274],"iteration":906,"passed_time":9.945503196,"remaining_time":1.019770449},
{"learn":[0.1608645489],"iteration":907,"passed_time":9.955684733,"remaining_time":1.008725766},
{"learn":[0.1608623111],"iteration":908,"passed_time":9.966170728,"remaining_time":0.9977134612},
{"learn":[0.1608124225],"iteration":909,"passed_time":9.977344263,"remaining_time":0.9867703117},
{"learn":[0.1607789167],"iteration":910,"passed_time":9.988903159,"remaining_time":0.9758643042},
{"learn":[0.1607159719],"iteration":911,"passed_time":10.00019101,"remaining_time":0.9649307115},
{"learn":[0.1606816917],"iteration":912,"passed_time":10.01034582,"remaining_time":0.9538883751},
{"learn":[0.1606226385],"iteration":913,"passed_time":10.02116615,"remaining_time":0.9429106002},
{"learn":[0.1605677115],"iteration":914,"passed_time":10.03209327,"remaining_time":0.9319430907},
{"learn":[0.1605103788],"iteration":915,"passed_time":10.04218641,"remaining_time":0.9208991903},
{"learn":[0.1604804429],"iteration":916,"passed_time":10.05297972,"remaining_time":0.9099207383},
{"learn":[0.1603867496],"iteration":917,"passed_time":10.0640227,"remaining_time":0.8989649907},
{"learn":[0.1602472833],"iteration":918,"passed_time":10.0748558,"remaining_time":0.8879905546},
{"learn":[0.1601900354],"iteration":919,"passed_time":10.08591077,"remaining_time":0.8770357194},
{"learn":[0.1601373493],"iteration":920,"passed_time":10.09680058,"remaining_time":0.8660664995},
{"learn":[0.1601348573],"iteration":921,"passed_time":10.10677065,"remaining_time":0.8550196426},
{"learn":[0.1600902896],"iteration":922,"passed_time":10.11752298,"remaining_time":0.8440403785},
{"learn":[0.1600239527],"iteration":923,"passed_time":10.1294113,"remaining_time":0.8331550418},
{"learn":[0.159976589],"iteration":924,"passed_time":10.13961084,"remaining_time":0.8221306085},
{"learn":[0.1599152704],"iteration":925,"passed_time":10.15088634,"remaining_time":0.8111939411},
{"learn":[0.1598337108],"iteration":926,"passed_time":10.17806165,"remaining_time":0.8015086301},
{"learn":[0.1597991848],"iteration":927,"passed_time":10.19269865,"remaining_time":0.7908128261},
{"learn":[0.1597130847],"iteration":928,"passed_time":10.20437547,"remaining_time":0.779882302},
{"learn":[0.1596465456],"iteration":929,"passed_time":10.21552149,"remaining_time":0.7689102199},
{"learn":[0.1596031915],"iteration":930,"passed_time":10.22630781,"remaining_time":0.7579111051},
{"learn":[0.1595498715],"iteration":931,"passed_time":10.23658501,"remaining_time":0.746875301},
{"learn":[0.1594838623],"iteration":932,"passed_time":10.24775794,"remaining_time":0.735905447},
{"learn":[0.1594275806],"iteration":933,"passed_time":10.2582034,"remaining_time":0.7248837518},
{"learn":[0.1593831804],"iteration":934,"passed_time":10.26904283,"remaining_time":0.7138906783},
{"learn":[0.1593172681],"iteration":935,"passed_time":10.28000428,"remaining_time":0.7029062756},
{"learn":[0.1592645888],"iteration":936,"passed_time":10.29051184,"remaining_time":0.6918914041},
{"learn":[0.1592018692],"iteration":937,"passed_time":10.30101063,"remaining_time":0.6808770351},
{"learn":[0.1591512911],"iteration":938,"passed_time":10.31231295,"remaining_time":0.6699159638},
{"learn":[0.1591494118],"iteration":939,"passed_time":10.32207954,"remaining_time":0.6588561406},
{"learn":[0.1591058906],"iteration":940,"passed_time":10.33271994,"remaining_time":0.6478538538},
{"learn":[0.1590692229],"iteration":941,"passed_time":10.34339211,"remaining_time":0.6368542912},
{"learn":[0.1590329555],"iteration":942,"passed_time":10.35361151,"remaining_time":0.6258280552},
{"learn":[0.158980838],"iteration":943,"passed_time":10.36437678,"remaining_time":0.6148359104},
{"learn":[0.1589709181],"iteration":944,"passed_time":10.3755938,"remaining_time":0.6038705386},
{"learn":[0.15889255],"iteration":945,"passed_time":10.38642851,"remaining_time":0.5928828112},
{"learn":[0.1587715482],"iteration":946,"passed_time":10.39768266,"remaining_time":0.5819188816},
{"learn":[0.1587433091],"iteration":947,"passed_time":10.4085403,"remaining_time":0.5709325902},
{"learn":[0.1587124734],"iteration":948,"passed_time":10.4185286,"remaining_time":0.5598998509},
{"learn":[0.1586535861],"iteration":949,"passed_time":10.42947331,"remaining_time":0.548919648},
{"learn":[0.1586515021],"iteration":950,"passed_time":10.44022305,"remaining_time":0.5379294737},
{"learn":[0.1585758574],"iteration":951,"passed_time":10.45084791,"remaining_time":0.5269335081},
{"learn":[0.1585434688],"iteration":952,"passed_time":10.46179576,"remaining_time":0.5159542505},
{"learn":[0.1584953331],"iteration":953,"passed_time":10.47237919,"remaining_time":0.5049574869},
{"learn":[0.1583942896],"iteration":954,"passed_time":10.48303817,"remaining_time":0.4939651494},
{"learn":[0.1583793049],"iteration":955,"passed_time":10.49358628,"remaining_time":0.4829684063},
{"learn":[0.1583093305],"iteration":956,"passed_time":10.50385937,"remaining_time":0.4719602434},
{"learn":[0.1582784564],"iteration":957,"passed_time":10.51429503,"remaining_time":0.4609607425},
{"learn":[0.1582430093],"iteration":958,"passed_time":10.52525085,"remaining_time":0.4499846558},
{"learn":[0.1582103841],"iteration":959,"passed_time":10.53533547,"remaining_time":0.4389723112},
{"learn":[0.158134708],"iteration":960,"passed_time":10.54615788,"remaining_time":0.4279918389},
{"learn":[0.1580887637],"iteration":961,"passed_time":10.55694957,"remaining_time":0.417010482},
{"learn":[0.1580357737],"iteration":962,"passed_time":10.56810137,"remaining_time":0.4060433548},
{"learn":[0.1579476298],"iteration":963,"passed_time":10.57882365,"remaining_time":0.3950598044},
{"learn":[0.1579224177],"iteration":964,"passed_time":10.58997015,"remaining_time":0.3840921816},
{"learn":[0.157880074],"iteration":965,"passed_time":10.60025962,"remaining_time":0.3730940239},
{"learn":[0.1578402598],"iteration":966,"passed_time":10.61099742,"remaining_time":0.3621126316},
{"learn":[0.1577751747],"iteration":967,"passed_time":10.6216593,"remaining_time":0.3511292329},
{"learn":[0.1576622309],"iteration":968,"passed_time":10.64031293,"remaining_time":0.340402168},
{"learn":[0.1576192427],"iteration":969,"passed_time":10.65085416,"remaining_time":0.3294078607},
{"learn":[0.157554436],"iteration":970,"passed_time":10.6621404,"remaining_time":0.318436737},
{"learn":[0.1574963386],"iteration":971,"passed_time":10.67323582,"remaining_time":0.3074594681},
{"learn":[0.1574366361],"iteration":972,"passed_time":10.68383089,"remaining_time":0.296468072},
{"learn":[0.1574348204],"iteration":973,"passed_time":10.69382027,"remaining_time":0.2854613213},
{"learn":[0.1573964001],"iteration":974,"passed_time":10.70453936,"remaining_time":0.2744753681},
{"learn":[0.1573948128],"iteration":975,"passed_time":10.71467792,"remaining_time":0.2634756866},
{"learn":[0.1573453116],"iteration":976,"passed_time":10.72511516,"remaining_time":0.252484799},
{"learn":[0.1572904536],"iteration":977,"passed_time":10.73604875,"remaining_time":0.2415062092},
{"learn":[0.1572614031],"iteration":978,"passed_time":10.74626749,"remaining_time":0.2305123772},
{"learn":[0.1572098076],"iteration":979,"passed_time":10.75704687,"remaining_time":0.2195315688},
{"learn":[0.1570731928],"iteration":980,"passed_time":10.76870707,"remaining_time":0.2085682307},
{"learn":[0.1570690245],"iteration":981,"passed_time":10.77864639,"remaining_time":0.1975719297},
{"learn":[0.1570542679],"iteration":982,"passed_time":10.78912925,"remaining_time":0.1865871793},
{"learn":[0.1570006812],"iteration":983,"passed_time":10.79977282,"remaining_time":0.1756060621},
{"learn":[0.1569587066],"iteration":984,"passed_time":10.80984871,"remaining_time":0.1646169855},
{"learn":[0.1569154355],"iteration":985,"passed_time":10.82054506,"remaining_time":0.1536385709},
{"learn":[0.1568012181],"iteration":986,"passed_time":10.83100442,"remaining_time":0.1426576063},
{"learn":[0.1567618337],"iteration":987,"passed_time":10.84169076,"remaining_time":0.1316804546},
{"learn":[0.1567603978],"iteration":988,"passed_time":10.85199005,"remaining_time":0.120699586},
{"learn":[0.156685646],"iteration":989,"passed_time":10.86443518,"remaining_time":0.1097417695},
{"learn":[0.1566682637],"iteration":990,"passed_time":10.87571709,"remaining_time":0.09877038732},
{"learn":[0.1566413208],"iteration":991,"passed_time":10.88734689,"remaining_time":0.08780118463},
{"learn":[0.1566303178],"iteration":992,"passed_time":10.89886919,"remaining_time":0.0768298936},
{"learn":[0.1565738674],"iteration":993,"passed_time":10.90992134,"remaining_time":0.065854656},
{"learn":[0.1564987966],"iteration":994,"passed_time":10.92135538,"remaining_time":0.0548811828},
{"learn":[0.1564503732],"iteration":995,"passed_time":10.93237894,"remaining_time":0.04390513631},
{"learn":[0.1564485602],"iteration":996,"passed_time":10.94232512,"remaining_time":0.03292575261},
{"learn":[0.1563810042],"iteration":997,"passed_time":10.95459679,"remaining_time":0.02195309978},
{"learn":[0.1563236964],"iteration":998,"passed_time":10.96585658,"remaining_time":0.01097683341},
{"learn":[0.1562623423],"iteration":999,"passed_time":10.97650614,"remaining_time":0}
]}